Workbook

Sheet ANNEE
C1: TABLEAU ANNUEL
A2: Saisir l'année du budget: | C2: 2026

Sheet TABLEAU ANNUEL
B1: TABLEAU ANNUEL
B2: =ANNEE!C2 -> 2026
B6: DESCRIPTION | C6: REVENUS | D6: DEPENSES | E6: ECONOMIE MENSUEL REALISE
B7: JANVIER | C7: {=INDIRECT("'" & $B7 & "'!G24")} -> 628.42 | D7: {=INDIRECT("'" & $B7 & "'!G25")} -> 428.31 | E7: =Tableau27[[#This Row],[REVENUS]]-Tableau27[[#This Row],[DEPENSES]] -> 200.11
B8: FÉVRIER | C8: {=INDIRECT("'" & $B8 & "'!G24")} -> 1154.22 | D8: {=INDIRECT("'" & $B8 & "'!G25")} -> 485.21 | E8: =Tableau27[[#This Row],[REVENUS]]-Tableau27[[#This Row],[DEPENSES]] -> 669.01
B9: MARS | C9: {=INDIRECT("'" & $B9 & "'!G24")} -> 0 | D9: {=INDIRECT("'" & $B9 & "'!G25")} -> 717.21 | E9: =Tableau27[[#This Row],[REVENUS]]-Tableau27[[#This Row],[DEPENSES]] -> -717.21
B10: AVRIL | C10: {=INDIRECT("'" & $B10 & "'!G24")} -> 2194.19 | D10: {=INDIRECT("'" & $B10 & "'!G25")} -> 455.51 | E10: =Tableau27[[#This Row],[REVENUS]]-Tableau27[[#This Row],[DEPENSES]] -> 1738.68
B11: MAI | C11: {=INDIRECT("'" & $B11 & "'!G24")} -> 2611.62 | D11: {=INDIRECT("'" & $B11 & "'!G25")} -> 569.7 | E11: =Tableau27[[#This Row],[REVENUS]]-Tableau27[[#This Row],[DEPENSES]] -> 2041.92
B12: JUIN | C12: {=INDIRECT("'" & $B12 & "'!G24")} -> 693.57 | D12: {=INDIRECT("'" & $B12 & "'!G25")} -> 1108.51 | E12: =Tableau27[[#This Row],[REVENUS]]-Tableau27[[#This Row],[DEPENSES]] -> -414.94
B13: JUILLET | C13: {=INDIRECT("'" & $B13 & "'!G24")} -> 853.81 | D13: {=INDIRECT("'" & $B13 & "'!G25")} -> 1108 | E13: =Tableau27[[#This Row],[REVENUS]]-Tableau27[[#This Row],[DEPENSES]] -> -254.19
B14: AOÛT | C14: {=INDIRECT("'" & $B14 & "'!G24")} -> 6589.41 | D14: {=INDIRECT("'" & $B14 & "'!G25")} -> 478.54 | E14: =Tableau27[[#This Row],[REVENUS]]-Tableau27[[#This Row],[DEPENSES]] -> 6110.87
B15: SEPTEMBRE | C15: {=INDIRECT("'" & $B15 & "'!G24")} -> 2567.54 | D15: {=INDIRECT("'" & $B15 & "'!G25")} -> 507.07 | E15: =Tableau27[[#This Row],[REVENUS]]-Tableau27[[#This Row],[DEPENSES]] -> 2060.47
B16: OCTOBRE | C16: {=INDIRECT("'" & $B16 & "'!G24")} -> 2200.61 | D16: {=INDIRECT("'" & $B16 & "'!G25")} -> 806.26 | E16: =Tableau27[[#This Row],[REVENUS]]-Tableau27[[#This Row],[DEPENSES]] -> 1394.35
B17: NOVEMBRE | C17: {=INDIRECT("'" & $B17 & "'!G24")} -> 8244.61 | D17: {=INDIRECT("'" & $B17 & "'!G25")} -> 582.25 | E17: =Tableau27[[#This Row],[REVENUS]]-Tableau27[[#This Row],[DEPENSES]] -> 7662.36
B18: DÉCEMBRE | C18: {=INDIRECT("'" & $B18 & "'!G24")} -> 1351.22 | D18: {=INDIRECT("'" & $B18 & "'!G25")} -> 846.3 | E18: =Tableau27[[#This Row],[REVENUS]]-Tableau27[[#This Row],[DEPENSES]] -> 504.92
B19: TOTAL ANNUEL | C19: =SUM(C7:C18) -> 29089.22 | D19: =SUM(D7:D18) -> 8092.87 | E19: =SUM(E7:E18) -> 20996.35
B22: DESCRIPTION | C22: PREVISION ECONOMIE MENSUELLE (budget) | D22: ECONOMIE MENSUELLE REALISE | E22: OBJECTIF ECONOMIE MENSUELLLE | F22: ECART ECONOMIE MENSUELLE REALISE / OBJECTIF | G22: ECART ECONOMIE MENSUELLE REALISE / BUDGET | H22: LE SOLDE BUDGETISE | I22: LE SOLDE ACUTELLE | J22: OBJECTIF SOLDE | K22: ECART SOLDE / OBJECTIF SOLDE
B23: JANVIER | C23: {=INDIRECT("'" & C$42 & "'!H" & 10)} -> 0 | D23: {=INDIRECT("'" & C$42 & "'!H" & 14)} -> 200.11 | E23: {=INDIRECT("'" & B23 & "'!L" & 10)} -> 10 | F23: =D23-E23 -> 190.11 | G23: =D23-C23 -> 200.11 | H23: {=INDIRECT("'" & C$42 & "'!B" & 10)} -> 157.97 | I23: {=INDIRECT("'" & C$42 & "'!B" & 14)} -> 358.08 | J23: {=INDIRECT("'" & C$42 & "'!B" & 14)} -> 358.08 | K23: =I23-J23 -> 0
B24: FÉVRIER | C24: {=INDIRECT("'" & D$42 & "'!H" & 10)} -> 0 | D24: {=INDIRECT("'" & D$42 & "'!H" & 14)} -> 669.01 | E24: {=INDIRECT("'" & B24 & "'!L" & 10)} -> 10 | F24: =D24-E24 -> 659.01 | G24: =D24-C24 -> 669.01 | H24: {=INDIRECT("'" & D$42 & "'!B" & 10)} -> 358.08 | I24: {=INDIRECT("'" & D$42 & "'!B" & 14)} -> 1027.09 | J24: {=INDIRECT("'" & D$42 & "'!B" & 14)} -> 1027.09 | K24: =I24-J24 -> 0
B25: MARS | C25: {=INDIRECT("'" & E$42 & "'!H" & 10)} -> 0 | D25: {=INDIRECT("'" & E$42 & "'!H" & 14)} -> -717.21 | E25: {=INDIRECT("'" & B25 & "'!L" & 10)} -> 10 | F25: =D25-E25 -> -727.21 | G25: =D25-C25 -> -717.21 | H25: {=INDIRECT("'" & E$42 & "'!B" & 10)} -> 1027.09 | I25: {=INDIRECT("'" & E$42 & "'!B" & 14)} -> 309.88 | J25: {=INDIRECT("'" & E$42 & "'!B" & 14)} -> 309.88 | K25: =I25-J25 -> 0
B26: AVRIL | C26: {=INDIRECT("'" & F$42 & "'!H" & 10)} -> 0 | D26: {=INDIRECT("'" & F$42 & "'!H" & 14)} -> 1738.68 | E26: {=INDIRECT("'" & B26 & "'!L" & 10)} -> 10 | F26: =D26-E26 -> 1728.68 | G26: =D26-C26 -> 1738.68 | H26: {=INDIRECT("'" & F$42 & "'!B" & 10)} -> 309.88 | I26: {=INDIRECT("'" & F$42 & "'!B" & 14)} -> 2048.56 | J26: {=INDIRECT("'" & F$42 & "'!B" & 14)} -> 2048.56 | K26: =I26-J26 -> 0
B27: MAI | C27: {=INDIRECT("'" & G$42 & "'!H" & 10)} -> 0 | D27: {=INDIRECT("'" & G$42 & "'!H" & 14)} -> 2041.92 | E27: {=INDIRECT("'" & B27 & "'!L" & 10)} -> 10 | F27: =D27-E27 -> 2031.92 | G27: =D27-C27 -> 2041.92 | H27: {=INDIRECT("'" & G$42 & "'!B" & 10)} -> 2048.56 | I27: {=INDIRECT("'" & G$42 & "'!B" & 14)} -> 4090.48 | J27: {=INDIRECT("'" & G$42 & "'!B" & 14)} -> 4090.48 | K27: =I27-J27 -> 0
B28: JUIN | C28: {=INDIRECT("'" & H$42 & "'!H" & 10)} -> 0 | D28: {=INDIRECT("'" & H$42 & "'!H" & 14)} -> -414.94 | E28: {=INDIRECT("'" & B28 & "'!L" & 10)} -> 10 | F28: =D28-E28 -> -424.94 | G28: =D28-C28 -> -414.94 | H28: {=INDIRECT("'" & H$42 & "'!B" & 10)} -> 4090.48 | I28: {=INDIRECT("'" & H$42 & "'!B" & 14)} -> 3675.54 | J28: {=INDIRECT("'" & H$42 & "'!B" & 14)} -> 3675.54 | K28: =I28-J28 -> 0
B29: JUILLET | C29: {=INDIRECT("'" & I$42 & "'!H" & 10)} -> 0 | D29: {=INDIRECT("'" & I$42 & "'!H" & 14)} -> -254.19 | E29: {=INDIRECT("'" & B29 & "'!L" & 10)} -> 10 | F29: =D29-E29 -> -264.19 | G29: =D29-C29 -> -254.19 | H29: {=INDIRECT("'" & I$42 & "'!B" & 10)} -> 3675.54 | I29: {=INDIRECT("'" & I$42 & "'!B" & 14)} -> 3421.35 | J29: {=INDIRECT("'" & I$42 & "'!B" & 14)} -> 3421.35 | K29: =I29-J29 -> 0
B30: AOÛT | C30: {=INDIRECT("'" & J$42 & "'!H" & 10)} -> 992.1 | D30: {=INDIRECT("'" & J$42 & "'!H" & 14)} -> 6110.87 | E30: {=INDIRECT("'" & B30 & "'!L" & 10)} -> 10 | F30: =D30-E30 -> 6100.87 | G30: =D30-C30 -> 5118.77 | H30: {=INDIRECT("'" & J$42 & "'!B" & 10)} -> 4413.45 | I30: {=INDIRECT("'" & J$42 & "'!B" & 14)} -> 9532.22 | J30: {=INDIRECT("'" & J$42 & "'!B" & 14)} -> 9532.22 | K30: =I30-J30 -> 0
B31: SEPTEMBRE | C31: {=INDIRECT("'" & K$42 & "'!H" & 10)} -> 0 | D31: {=INDIRECT("'" & K$42 & "'!H" & 14)} -> 2060.47 | E31: {=INDIRECT("'" & B31 & "'!L" & 10)} -> 10 | F31: =D31-E31 -> 2050.47 | G31: =D31-C31 -> 2060.47 | H31: {=INDIRECT("'" & K$42 & "'!B" & 10)} -> 9532.22 | I31: {=INDIRECT("'" & K$42 & "'!B" & 14)} -> 11592.69 | J31: {=INDIRECT("'" & K$42 & "'!B" & 14)} -> 11592.69 | K31: =I31-J31 -> 0
B32: OCTOBRE | C32: {=INDIRECT("'" & L$42 & "'!H" & 10)} -> 0 | D32: {=INDIRECT("'" & L$42 & "'!H" & 14)} -> 1394.35 | E32: {=INDIRECT("'" & B32 & "'!L" & 10)} -> 10 | F32: =D32-E32 -> 1384.35 | G32: =D32-C32 -> 1394.35 | H32: {=INDIRECT("'" & L$42 & "'!B" & 10)} -> 11592.69 | I32: {=INDIRECT("'" & L$42 & "'!B" & 14)} -> 12987.04 | J32: {=INDIRECT("'" & L$42 & "'!B" & 14)} -> 12987.04 | K32: =I32-J32 -> 0
B33: NOVEMBRE | C33: {=INDIRECT("'" & M$42 & "'!H" & 10)} -> 1441.18 | D33: {=INDIRECT("'" & M$42 & "'!H" & 14)} -> 7662.36 | E33: {=INDIRECT("'" & B33 & "'!L" & 10)} -> 10 | F33: =D33-E33 -> 7652.36 | G33: =D33-C33 -> 6221.18 | H33: {=INDIRECT("'" & M$42 & "'!B" & 10)} -> 14428.22 | I33: {=INDIRECT("'" & M$42 & "'!B" & 14)} -> 20649.4 | J33: {=INDIRECT("'" & M$42 & "'!B" & 14)} -> 20649.4 | K33: =I33-J33 -> 0
B34: DÉCEMBRE | C34: {=INDIRECT("'" & N$42 & "'!H" & 10)} -> 0 | D34: {=INDIRECT("'" & N$42 & "'!H" & 14)} -> 504.92 | E34: {=INDIRECT("'" & B34 & "'!L" & 10)} -> 200 | F34: =D34-E34 -> 304.92 | G34: =D34-C34 -> 504.92 | H34: {=INDIRECT("'" & N$42 & "'!B" & 10)} -> 20649.4 | I34: {=INDIRECT("'" & N$42 & "'!B" & 14)} -> 21154.32 | J34: {=INDIRECT("'" & N$42 & "'!B" & 14)} -> 21154.32 | K34: =I34-J34 -> 0
B35: TOTAL ANNUEL | C35: =SUM(C23:C34) -> 2433.28 | D35: =SUM(D23:D34) -> 20996.35 | E35: =SUM(E23:E34) -> 310 | H35: =MAX(H23:H34) -> 20649.4 | I35: =MAX(I23:I34) -> 21154.32 | J35: =MAX(J23:J34) -> 21154.32
B42: DESCRIPTION | C42: JANVIER | D42: FÉVRIER | E42: MARS | F42: AVRIL | G42: MAI | H42: JUIN | I42: JUILLET | J42: AOÛT | K42: SEPTEMBRE | L42: OCTOBRE | M42: NOVEMBRE | N42: DÉCEMBRE | O42: TOTAL ANNUEL
B43: REVENUS | C43: {=INDIRECT("'" & $C$42 & "'!G24")} -> 628.42 | D43: {=INDIRECT("'" & $D$42 & "'!G24")} -> 1154.22 | E43: {=INDIRECT("'" & E$42 & "'!G24")} -> 0 | F43: {=INDIRECT("'" & $F$42 & "'!G24")} -> 2194.19 | G43: {=INDIRECT("'" & $G$42 & "'!G24")} -> 2611.62 | H43: {=INDIRECT("'" & $H$42 & "'!G24")} -> 693.57 | I43: {=INDIRECT("'" & $I$42 & "'!G24")} -> 853.81 | J43: {=INDIRECT("'" & $J$42 & "'!G24")} -> 6589.41 | K43: {=INDIRECT("'" & $K$42 & "'!G24")} -> 2567.54 | L43: {=INDIRECT("'" & $L$42 & "'!G24")} -> 2200.61 | M43: {=INDIRECT("'" & $M$42 & "'!G24")} -> 8244.61 | N43: {=INDIRECT("'" & $H$42 & "'!G24")} -> 693.57 | O43: =SUM(C43:N43) -> 28431.57
B44: DEPENSES | C44: {=INDIRECT("'" & $C$42 & "'!G25")} -> 428.31 | D44: {=INDIRECT("'" & D$42 & "'!G25")} -> 485.21 | E44: {=INDIRECT("'" & E$42 & "'!G25")} -> 717.21 | F44: {=INDIRECT("'" & F$42 & "'!G25")} -> 455.51 | G44: {=INDIRECT("'" & G$42 & "'!G25")} -> 569.7 | H44: {=INDIRECT("'" & H$42 & "'!G25")} -> 1108.51 | I44: {=INDIRECT("'" & I$42 & "'!G25")} -> 1108 | J44: {=INDIRECT("'" & J$42 & "'!G25")} -> 478.54 | K44: {=INDIRECT("'" & K$42 & "'!G25")} -> 507.07 | ... N44: {=INDIRECT("'" & N$42 & "'!G25")} -> 846.3 | O44: =SUM(C44:N44) -> 8092.87
B45: ECONOMIE MENSUEL REALISE | C45: =C43-SUM(C44:C44) -> 200.11 | D45: =D43-SUM(D44:D44) -> 669.01 | E45: =E43-SUM(E44:E44) -> -717.21 | F45: =F43-SUM(F44:F44) -> 1738.68 | G45: =G43-SUM(G44:G44) -> 2041.92 | H45: =H43-SUM(H44:H44) -> -414.94 | I45: =I43-SUM(I44:I44) -> -254.19 | J45: =J43-SUM(J44:J44) -> 6110.87 | ... N45: =N43-SUM(N44:N44) -> -152.73 | O45: =SUM(C45:N45) -> 20338.7
B48: DESCRIPTION | C48: JANVIER | D48: FÉVRIER | E48: MARS | F48: AVRIL | G48: MAI | H48: JUIN | I48: JUILLET | J48: AOÛT | K48: SEPTEMBRE | L48: OCTOBRE | M48: NOVEMBRE | N48: DÉCEMBRE | O48: TOTAL ANNUEL
B49: PREVISION ECONOMIE MENSUELLE (budget) | C49: {=INDIRECT("'" & C$42 & "'!H" & 10)} -> 0 | D49: {=INDIRECT("'" & D$42 & "'!H" & 10)} -> 0 | E49: {=INDIRECT("'" & E$42 & "'!H" & 10)} -> 0 | F49: {=INDIRECT("'" & F$42 & "'!H" & 10)} -> 0 | G49: {=INDIRECT("'" & G$42 & "'!H" & 10)} -> 0 | H49: {=INDIRECT("'" & H$42 & "'!H" & 10)} -> 0 | I49: {=INDIRECT("'" & I$42 & "'!H" & 10)} -> 0 | J49: {=INDIRECT("'" & J$42 & "'!H" & 10)} -> 992.1 | ... N49: {=INDIRECT("'" & N$42 & "'!H" & 10)} -> 0 | O49: =SUM(C49:N49) -> 2433.28
B50: ECONOMIE MENSUELLE REALISE | C50: {=INDIRECT("'" & C$42 & "'!H" & 14)} -> 200.11 | D50: {=INDIRECT("'" & D$42 & "'!H" & 14)} -> 669.01 | E50: {=INDIRECT("'" & E$42 & "'!H" & 14)} -> -717.21 | F50: {=INDIRECT("'" & F$42 & "'!H" & 14)} -> 1738.68 | G50: {=INDIRECT("'" & G$42 & "'!H" & 14)} -> 2041.92 | H50: {=INDIRECT("'" & H$42 & "'!H" & 14)} -> -414.94 | I50: {=INDIRECT("'" & I$42 & "'!H" & 14)} -> -254.19 | J50: {=INDIRECT("'" & J$42 & "'!H" & 14)} -> 6110.87 | ... N50: {=INDIRECT("'" & N$42 & "'!H" & 14)} -> 504.92 | O50: =SUM(C50:N50) -> 20996.35
B51: OBJECTIF ECONOMIE MENSUELLLE | C51: {=INDIRECT("'" & C$42 & "'!L" & 10)} -> 10 | D51: {=INDIRECT("'" & D$42 & "'!L" & 10)} -> 10 | E51: {=INDIRECT("'" & E$42 & "'!L" & 10)} -> 10 | F51: {=INDIRECT("'" & F$42 & "'!L" & 10)} -> 10 | G51: {=INDIRECT("'" & G$42 & "'!L" & 10)} -> 10 | H51: {=INDIRECT("'" & H$42 & "'!L" & 10)} -> 10 | I51: {=INDIRECT("'" & I$42 & "'!L" & 10)} -> 10 | J51: {=INDIRECT("'" & J$42 & "'!L" & 10)} -> 10 | ... N51: {=INDIRECT("'" & N$42 & "'!L" & 10)} -> 200 | O51: =SUM(C51:N51) -> 310
B52: ECART ECONOMIE MENSUELLE REALISE / OBJECTIF | C52: =C50-C51 -> 190.11 | D52: =D50-D51 -> 659.01 | E52: =E50-E51 -> -727.21 | F52: =F50-F51 -> 1728.68 | G52: =G50-G51 -> 2031.92 | H52: =H50-H51 -> -424.94 | I52: =I50-I51 -> -264.19 | J52: =J50-J51 -> 6100.87 | ... N52: =N50-N51 -> 304.92
B53: ECART ECONOMIE MENSUELLE REALISE / BUDGET | C53: =C50-C49 -> 200.11 | D53: =D50-D49 -> 669.01 | E53: =E50-E49 -> -717.21 | F53: =F50-F49 -> 1738.68 | G53: =G50-G49 -> 2041.92 | H53: =H50-H49 -> -414.94 | I53: =I50-I49 -> -254.19 | J53: =J50-J49 -> 5118.77 | ... N53: =N50-N49 -> 504.92
B54: LE SOLDE BUDGETISE | C54: {=INDIRECT("'" & C$42 & "'!B" & 10)} -> 157.97 | D54: {=INDIRECT("'" & D$42 & "'!B" & 10)} -> 358.08 | E54: {=INDIRECT("'" & E$42 & "'!B" & 10)} -> 1027.09 | F54: {=INDIRECT("'" & F$42 & "'!B" & 10)} -> 309.88 | G54: {=INDIRECT("'" & G$42 & "'!B" & 10)} -> 2048.56 | H54: {=INDIRECT("'" & H$42 & "'!B" & 10)} -> 4090.48 | I54: {=INDIRECT("'" & I$42 & "'!B" & 10)} -> 3675.54 | J54: {=INDIRECT("'" & J$42 & "'!B" & 10)} -> 4413.45 | ... N54: {=INDIRECT("'" & N$42 & "'!B" & 10)} -> 20649.4 | O54: =MAX(Tableau31[[#This Row],[JANVIER]:[DÉCEMBRE]]) -> 20649.4
B55: LE SOLDE ACUTELLE | C55: {=INDIRECT("'" & C$42 & "'!B" & 14)} -> 358.08 | D55: {=INDIRECT("'" & D$42 & "'!B" & 14)} -> 1027.09 | E55: {=INDIRECT("'" & E$42 & "'!B" & 14)} -> 309.88 | F55: {=INDIRECT("'" & F$42 & "'!B" & 14)} -> 2048.56 | G55: {=INDIRECT("'" & G$42 & "'!B" & 14)} -> 4090.48 | H55: {=INDIRECT("'" & H$42 & "'!B" & 14)} -> 3675.54 | I55: {=INDIRECT("'" & I$42 & "'!B" & 14)} -> 3421.35 | J55: {=INDIRECT("'" & J$42 & "'!B" & 14)} -> 9532.22 | ... N55: {=INDIRECT("'" & N$42 & "'!B" & 14)} -> 21154.32 | O55: =MAX(Tableau31[[#This Row],[JANVIER]:[DÉCEMBRE]]) -> 21154.32
B56: OBJECTIF SOLDE | C56: {=INDIRECT("'" & C$42 & "'!L" & 14)} -> 167.97 | D56: {=INDIRECT("'" & D$42 & "'!L" & 14)} -> 368.08 | E56: {=INDIRECT("'" & E$42 & "'!L" & 14)} -> 1037.09 | F56: {=INDIRECT("'" & F$42 & "'!L" & 14)} -> 319.88 | G56: {=INDIRECT("'" & G$42 & "'!L" & 14)} -> 2058.56 | H56: {=INDIRECT("'" & H$42 & "'!L" & 14)} -> 4100.48 | I56: {=INDIRECT("'" & I$42 & "'!L" & 14)} -> 3685.54 | J56: {=INDIRECT("'" & J$42 & "'!L" & 14)} -> 3431.35 | ... N56: {=INDIRECT("'" & N$42 & "'!L" & 14)} -> 20849.4 | O56: =MAX(Tableau31[[#This Row],[JANVIER]:[DÉCEMBRE]]) -> 20849.4
B57: ECART SOLDE / OBJECTIF SOLDE | C57: =C55-C56 -> 190.11 | D57: =D55-D56 -> 659.01 | E57: =E55-E56 -> -727.21 | F57: =F55-F56 -> 1728.68 | G57: =G55-G56 -> 2031.92 | H57: =H55-H56 -> -424.94 | I57: =I55-I56 -> -264.19 | J57: =J55-J56 -> 6100.87 | ... N57: =N55-N56 -> 304.92

Sheet Résumé BUDGET Mensuel
E1: TABLEAU ANNUEL
E2: ='TABLEAU ANNUEL'!B2 -> 2026
E3: *
A4: RÉSUMÉ DU BUDGET
B6: REEL | E6: REVENU ANNUEL | G6: DEPENSE ANNUELLE | I6: ECONOMIES ANNUELLES | K6: MOIS LE PLUS ECONOMIQUE | M6: MOIS LE PLUS DEPENSIER | O6: MOIS LE PLUS LUCRATIF
E7: ='TABLEAU ANNUEL'!C19 -> 29089.22 | G7: ='TABLEAU ANNUEL'!D19 -> 8092.87 | I7: ='TABLEAU ANNUEL'!E19 -> 20996.35 | K7: =INDEX('TABLEAU ANNUEL'!C42:N42,MATCH(MAX('TABLEAU ANNUEL'!C45:N45),'TABLEAU ANNUEL'!C45:N45,0)) -> NOVEMBRE | M7: =INDEX('TABLEAU ANNUEL'!C42:N42,MATCH(MAX('TABLEAU ANNUEL'!C44:N44),'TABLEAU ANNUEL'!C44:N44,0)) -> JUIN | O7: =INDEX('TABLEAU ANNUEL'!C42:N42,MATCH(MAX('TABLEAU ANNUEL'!C43:N43),'TABLEAU ANNUEL'!C43:N43,0)) -> NOVEMBRE
K10: MOIS LE MOINS ECONOMIQUE | M10: MOIS LE MOINS DEPENSIER | O10: MOIS LE MOINS LUCRATIF
K11: =INDEX('TABLEAU ANNUEL'!C42:N42,MATCH(MIN('TABLEAU ANNUEL'!C45:N45),'TABLEAU ANNUEL'!C45:N45,0)) -> MARS | M11: =INDEX('TABLEAU ANNUEL'!C42:N42,MATCH(MIN('TABLEAU ANNUEL'!C44:N44),'TABLEAU ANNUEL'!C44:N44,0)) -> JANVIER | O11: {=INDEX('TABLEAU ANNUEL'!C42:N42,MATCH(SMALL(IF('TABLEAU ANNUEL'!C43:N43>0,'TABLEAU ANNUEL'!C43:N43),1),'TABLEAU ANNUEL'!C43:N43,0))} -> JANVIER
B19: PROVISOIRE | E19: ECONOMIES ANNUELLES
E20: ='TABLEAU ANNUEL'!O49 -> 2433.28
B27: OBJECTIF | E27: SOLDE ANNUELLE | G27: ECONOMIES ANNUELLES
E28: ='TABLEAU ANNUEL'!O56 -> 20849.4 | G28: ='TABLEAU ANNUEL'!O51 -> 310

Sheet Résumé BUDGET Trimestriel
E1: TABLEAU ANNUEL
E2: ='TABLEAU ANNUEL'!B2 -> 2026
A4: RÉSUMÉ DU BUDGET
B6: REEL | E6: REVENU ANNUEL | G6: DEPENSE ANNUELLE | I6: ECONOMIES ANNUELLES | K6: TRIMESTRE LE PLUS ECONOMIQUE | M6: TRIMESTRE LE PLUS DEPENSIER | O6: TRIMESTRE LE PLUS LUCRATIF
E7: ='TABLEAU TRIMESTRIEL'!C9 -> 26655.94 | G7: ='TABLEAU TRIMESTRIEL'!D9 -> 8092.87 | I7: ='TABLEAU TRIMESTRIEL'!E9 -> 11638.02 | K7: =INDEX('TABLEAU TRIMESTRIEL'!C13:F13,MATCH(MAX('TABLEAU TRIMESTRIEL'!C16:F16),'TABLEAU TRIMESTRIEL'!C16:F16,0)) -> T4 | M7: =INDEX('TABLEAU TRIMESTRIEL'!C13:F13,MATCH(MAX('TABLEAU TRIMESTRIEL'!C15:F15),'TABLEAU TRIMESTRIEL'!C15:F15,0)) -> T3 | O7: =INDEX('TABLEAU TRIMESTRIEL'!C13:F13,MATCH(MAX('TABLEAU TRIMESTRIEL'!C14:F14),'TABLEAU TRIMESTRIEL'!C14:F14,0)) -> T4
K10: TRIMESTRE LE MOINS ECONOMIQUE | M10: TRIMESTRE LE MOINS DEPENSIER | O10: TRIMESTRE LE MOINS LUCRATIF
K11: =INDEX('TABLEAU TRIMESTRIEL'!C13:F13,MATCH(MIN('TABLEAU TRIMESTRIEL'!C16:F16),'TABLEAU TRIMESTRIEL'!C16:F16,0)) -> T3 | M11: =INDEX('TABLEAU TRIMESTRIEL'!C13:F13,MATCH(MIN('TABLEAU TRIMESTRIEL'!C15:F15),'TABLEAU TRIMESTRIEL'!C15:F15,0)) -> T1 | O11: =INDEX('TABLEAU TRIMESTRIEL'!C13:F13,MATCH(MIN('TABLEAU TRIMESTRIEL'!C14:F14),'TABLEAU TRIMESTRIEL'!C14:F14,0)) -> T1
B15: PROVISOIRE | E15: ECONOMIES ANNUELLES
E16: ='TABLEAU TRIMESTRIEL'!C25 -> 9358.33
B21: OBJECTIF | E21: SOLDE ANNUELLE | G21: ECONOMIES ANNUELLES
E22: ='TABLEAU ANNUEL'!O56 -> 20849.4 | G22: ='TABLEAU TRIMESTRIEL'!G16 -> 11638.02

Sheet TABLEAU TRIMESTRIEL
B1: TABLEAU TRIMESTRIEL
B2: ='TABLEAU ANNUEL'!B2 -> 2026
B4: TRIMESTRE | C4: REVENUS | D4: DEPENSES | E4: ECONOMIE TRIMESTRIELLE
B5: T1 | C5: =SUM($C41:$E41) -> 1782.64 | D5: =SUM($C42:$E42) -> 1630.73 | E5: =SUM($C43:$E43) -> 151.91
B6: T2 | C6: =SUM($F41:$H41) -> 5499.38 | D6: =SUM($F42:$H42) -> 2133.72 | E6: =SUM($F43:$H43) -> 3365.66
B7: T3 | C7: =SUM($I41:$K41) -> 9018.66 | D7: =SUM($I42:$K42) -> 2093.61 | E7: =SUM($I44:$K44) -> 0
B8: T4 | C8: =SUM($L41:$N41) -> 10355.26 | D8: =SUM($L42:$N42) -> 2234.81 | E8: =SUM($L43:$N43) -> 8120.45
B9: TOTAL ANNUEL | C9: =SUM(C5:C8) -> 26655.94 | D9: =SUM(D5:D8) -> 8092.87 | E9: =SUM(E5:E8) -> 11638.02
B13: TRIMESTRE | C13: T1 | D13: T2 | E13: T3 | F13: T4 | G13: TOTAL ANNUEL
B14: REVENUS | C14: =SUM(C41:E41) -> 1782.64 | D14: =SUM(F41:H41) -> 5499.38 | E14: =SUM(I42:K42) -> 2093.61 | F14: =SUM(L41:N41) -> 10355.26 | G14: =SUM(C14:F14) -> 19730.89
B15: DEPENSES | C15: =SUM(C42:E42) -> 1630.73 | D15: =SUM(F42:H42) -> 2133.72 | E15: =SUM(I43:K43) -> 6925.05 | F15: =SUM(L42:N42) -> 2234.81 | G15: =SUM(C15:F15) -> 12924.31
B16: ECONOMIE TRIMESTRIELLE | C16: =SUM(C43:E43) -> 151.91 | D16: =SUM(F43:H43) -> 3365.66 | E16: =SUM(I44:K44) -> 0 | F16: =SUM(L43:N43) -> 8120.45 | G16: =SUM(C16:F16) -> 11638.02
B20: TRISMESTRE | C20: PREVISION ECONOMIE TRIMESTRIELLE (budget) | D20: ECONOMIE TRIMESTRIELLE REALISE | E20: OBJECTIF ECONOMIE TRIMESTRIELLE | F20: ECART ECONOMIE - OBJECTIF | G20: LE SOLDE BUDGETISE | H20: LE SOLDE | I20: OBJECTIF SOLDE | J20: ECART SOLDE
B21: T1 | C21: =SUM(C59:E59) -> 0 | D21: =SUM(C60:E60) -> 151.91 | E21: =SUM(C61:E61) -> 0 | F21: =D21-E21 -> 151.91 | G21: =E63 -> 1027.09 | H21: =E64 -> 309.88 | I21: =E65 -> 0 | J21: =H21-I21 -> 309.88
B22: T2 | C22: =SUM(F59:H59) -> 0 | D22: =SUM(F60:H60) -> 3365.66 | E22: =SUM(G61:I61) -> 0 | F22: =D22-E22 -> 3365.66 | G22: =H63 -> 4090.48 | H22: =H64 -> 3675.54 | I22: =H65 -> 0 | J22: =H22-I22 -> 3675.54
B23: T3 | C23: =SUM(I60:K60) -> 7917.15 | D23: =SUM(J61:L61) -> 0 | E23: =SUM(I62:K62) -> 6925.05 | F23: =D23-E23 -> -6925.05 | G23: =K63 -> 9532.22 | H23: =K64 -> 11592.69 | I23: =K65 -> 0 | J23: =H23-I23 -> 11592.69
B24: T4 | C24: =SUM(L59:N59) -> 1441.18 | D24: =SUM(L60:N60) -> 9561.63 | E24: =SUM(L61:N61) -> 0 | F24: =D24-E24 -> 9561.63 | G24: =N63 -> 20649.4 | H24: =N64 -> 21154.32 | I24: =N65 -> 0 | J24: =H24-I24 -> 21154.32
B25: TOTAL ANNUEL | C25: =SUM(C21:C24) -> 9358.33 | D25: =SUM(D21:D24) -> 13079.2 | E25: =SUM(E21:E24) -> 6925.05 | F25: =D25-E25 -> 6154.15
B28: TRISMESTRE | C28: T1 | D28: T2 | E28: T3 | F28: T4 | G28: TOTAL ANNUEL
B29: PREVISION ECONOMIE TRIMESTRIELLE (budget) | C29: =SUM(C59:E59) -> 0 | D29: =SUM(F59:H59) -> 0 | E29: =SUM(I60:K60) -> 7917.15 | F29: =SUM(L59:N59) -> 1441.18 | G29: =SUM(C29:F29) -> 9358.33
B30: ECONOMIE TRIMESTRIELLE REALISE | C30: =SUM(C60:E60) -> 151.91 | D30: =SUM(F60:H60) -> 3365.66 | E30: =SUM(I61:K61) -> 0 | F30: =SUM(L60:N60) -> 9561.63 | G30: =SUM(C30:F30) -> 13079.2
B31: OBJECTIF ECONOMIE TRIMESTRIELLE | C31: =SUM(C61:E61) -> 0 | D31: =SUM(F61:H61) -> 0 | E31: =SUM(I62:K62) -> 6925.05 | F31: =SUM(L61:N61) -> 0 | G31: =SUM(C31:F31) -> 6925.05
B32: ECART ECONOMIE - OBJECTIF | C32: =C30-C31 -> 151.91 | D32: =D30-D31 -> 3365.66 | E32: =E30-E31 -> -6925.05 | F32: =F30-F31 -> 9561.63 | G32: =G30-G31 -> 6154.15
B33: LE SOLDE BUDGETISE | C33: =E63 -> 1027.09 | D33: =H63 -> 4090.48 | E33: =K63 -> 9532.22 | F33: =N63 -> 20649.4
B34: LE SOLDE | C34: =E64 -> 309.88 | D34: =H64 -> 3675.54 | E34: =K64 -> 11592.69 | F34: =N64 -> 21154.32
B35: OBJECTIF SOLDE | C35: =E65 -> 0 | D35: =H65 -> 0 | E35: =K65 -> 0 | F35: =N65 -> 0
B36: ECART SOLDE- OBJECTIF | C36: =C34-C35 -> 309.88 | D36: =D34-D35 -> 3675.54 | E36: =E34-E35 -> 11592.69 | F36: =F34-F35 -> 21154.32
B40: MOIS | C40: JANVIER | D40: FÉVRIER | E40: MARS | F40: AVRIL | G40: MAI | H40: JUIN | I40: JUILLET | J40: AOÛT | K40: SEPTEMBRE | L40: OCTOBRE | M40: NOVEMBRE | N40: DÉCEMBRE | O40: TOTAL ANNUEL
B41: REVENUS | C41: {=INDIRECT("'" & $C$40 & "'!H24")} -> 628.42 | D41: {=INDIRECT("'" & D$40 & "'!H24")} -> 1154.22 | E41: {=INDIRECT("'" & E$40 & "'!H24")} -> 0 | F41: {=INDIRECT("'" & F$40 & "'!H24")} -> 2194.19 | G41: {=INDIRECT("'" & G$40 & "'!H24")} -> 2611.62 | H41: {=INDIRECT("'" & H$40 & "'!H24")} -> 693.57 | I41: {=INDIRECT("'" & I$40 & "'!H24")} -> 853.81 | J41: {=INDIRECT("'" & J$40 & "'!H24")} -> 5597.31 | K41: {=INDIRECT("'" & K$40 & "'!H24")} -> 2567.54 | ... N41: {=INDIRECT("'" & N$40 & "'!H24")} -> 1351.22 | O41: =SUM(C41:N41) -> 26655.94
B42: DEPENSES | C42: {=INDIRECT("'" & $C$40 & "'!H25")} -> 428.31 | D42: {=INDIRECT("'" & D$40 & "'!H25")} -> 485.21 | E42: {=INDIRECT("'" & E$40 & "'!H25")} -> 717.21 | F42: {=INDIRECT("'" & F$40 & "'!H25")} -> 455.51 | G42: {=INDIRECT("'" & G$40 & "'!H25")} -> 569.7 | H42: {=INDIRECT("'" & H$40 & "'!H25")} -> 1108.51 | I42: {=INDIRECT("'" & I$40 & "'!H25")} -> 1108 | J42: {=INDIRECT("'" & J$40 & "'!H25")} -> 478.54 | K42: {=INDIRECT("'" & K$40 & "'!H25")} -> 507.07 | ... N42: {=INDIRECT("'" & N$40 & "'!H25")} -> 846.3 | O42: =SUM(C42:N42) -> 8092.87
B43: ECONOMIE MENSUELLE | C43: =C41-SUM(C42:C42) -> 200.11 | D43: =D41-SUM(D42:D42) -> 669.01 | E43: =E41-SUM(E42:E42) -> -717.21 | F43: =F41-SUM(F42:F42) -> 1738.68 | G43: =G41-SUM(G42:G42) -> 2041.92 | H43: =H41-SUM(H42:H42) -> -414.94 | I43: =I41-SUM(I42:I42) -> -254.19 | J43: =J41-SUM(J42:J42) -> 5118.77 | ... N43: =N41-SUM(N42:N42) -> 504.92 | O43: =SUM(C43:N43) -> 18563.07
B48: TRISMESTRE | C48: T1 | D48: T2 | E48: T3 | F48: T4 | G48: TOTAL ANNUEL
B49: PREVISION ECONOMIE TRIMESTRIELLE (budget) | C49: =SUM(C59:E59) -> 0 | D49: =SUM(F59:H59) -> 0 | E49: =SUM(I60:K60) -> 7917.15 | F49: =SUM(L59:N59) -> 1441.18 | G49: =SUM(C49:F49) -> 9358.33
B50: ECONOMIE TRIMESTRIELLE REALISE | C50: =SUM(C60:E60) -> 151.91 | D50: =SUM(F60:H60) -> 3365.66 | E50: =SUM(J61:L61) -> 0 | F50: =SUM(L60:N60) -> 9561.63 | G50: =SUM(C50:F50) -> 13079.2
B51: OBJECTIF ECONOMIE TRIMESTRIELLE | C51: =SUM(C61:E61) -> 0 | D51: =SUM(F61:H61) -> 0 | E51: =SUM(I62:K62) -> 6925.05 | F51: =SUM(L61:N61) -> 0 | G51: =SUM(C51:F51) -> 6925.05
B52: ECART ECONOMIE - OBJECTIF | C52: =C50-C51 -> 151.91 | D52: =D50-D51 -> 3365.66 | E52: =E50-E51 -> -6925.05 | F52: =F50-F51 -> 9561.63
B53: LE SOLDE BUDGETISE | C53: =E63 -> 1027.09 | D53: =H63 -> 4090.48 | E53: =K63 -> 9532.22 | F53: =N63 -> 20649.4
B54: LE SOLDE | C54: =E64 -> 309.88 | D54: =H64 -> 3675.54 | E54: =K64 -> 11592.69 | F54: =N64 -> 21154.32
B55: OBJECTIF SOLDE | C55: =E65 -> 0 | D55: =H65 -> 0 | E55: =K65 -> 0 | F55: =N65 -> 0
B56: ECART SOLDE | C56: =C54-C55 -> 309.88 | D56: =D54-D55 -> 3675.54 | E56: =E54-E55 -> 11592.69 | F56: =F54-F55 -> 21154.32
B58: DESCRIPTION | C58: JANVIER | D58: FÉVRIER | E58: MARS | F58: AVRIL | G58: MAI | H58: JUIN | I58: JUILLET | J58: AOÛT | K58: SEPTEMBRE | L58: OCTOBRE | M58: NOVEMBRE | N58: DÉCEMBRE
B59: PREVISION ECONOMIE MENSUELLE (budget) | C59: {=INDIRECT("'" & C$40 & "'!H" & 10)} -> 0 | D59: {=INDIRECT("'" & D$40 & "'!H" & 10)} -> 0 | E59: {=INDIRECT("'" & E$40 & "'!H" & 10)} -> 0 | F59: {=INDIRECT("'" & F$40 & "'!H" & 10)} -> 0 | G59: {=INDIRECT("'" & G$40 & "'!H" & 10)} -> 0 | H59: {=INDIRECT("'" & H$40 & "'!H" & 10)} -> 0 | I59: {=INDIRECT("'" & I$40 & "'!H" & 10)} -> 0 | J59: {=INDIRECT("'" & J$40 & "'!H" & 10)} -> 992.1 | ... N59: {=INDIRECT("'" & N$40 & "'!H" & 10)} -> 0
B60: ECONOMIE MENSUELLE REALISEE | C60: {=INDIRECT("'" & C$40 & "'!H" & 14)} -> 200.11 | D60: {=INDIRECT("'" & D$40 & "'!H" & 14)} -> 669.01 | E60: {=INDIRECT("'" & E$40 & "'!H" & 14)} -> -717.21 | F60: {=INDIRECT("'" & F$40 & "'!H" & 14)} -> 1738.68 | G60: {=INDIRECT("'" & G$40 & "'!H" & 14)} -> 2041.92 | H60: {=INDIRECT("'" & H$40 & "'!H" & 14)} -> -414.94 | I60: {=INDIRECT("'" & I$40 & "'!H" & 14)} -> -254.19 | J60: {=INDIRECT("'" & J$40 & "'!H" & 14)} -> 6110.87 | ... N60: {=INDIRECT("'" & N$40 & "'!H" & 14)} -> 504.92
B61: OBJECTIF ECONOMIE MENSUELLE | C61: {=INDIRECT("'" & C$58 & "'!N" & 10)} -> 0 | D61: {=INDIRECT("'" & D$58 & "'!N" & 10)} -> 0 | E61: {=INDIRECT("'" & E$58 & "'!N" & 10)} -> 0 | F61: {=INDIRECT("'" & F$58 & "'!N" & 10)} -> 0 | G61: {=INDIRECT("'" & G$58 & "'!N" & 10)} -> 0 | H61: {=INDIRECT("'" & H$58 & "'!N" & 10)} -> 0 | I61: {=INDIRECT("'" & I$58 & "'!N" & 10)} -> 0 | J61: {=INDIRECT("'" & J$58 & "'!N" & 10)} -> 0 | ... N61: {=INDIRECT("'" & N$58 & "'!N" & 10)} -> 0
B62: ECART ECONOMIE REEL - BUDGET | C62: =C60-C59 -> 200.11 | D62: =D60-D59 -> 669.01 | E62: =E60-E59 -> -717.21 | F62: =F60-F59 -> 1738.68 | G62: =G60-G59 -> 2041.92 | H62: =H60-H59 -> -414.94 | I62: =I60-I59 -> -254.19 | J62: =J60-J59 -> 5118.77 | ... N62: =N60-N59 -> 504.92
B63: LE SOLDE BUDGETISE | C63: {=INDIRECT("'" & C$40 & "'!B" & 10)} -> 157.97 | D63: {=INDIRECT("'" & D$40 & "'!B" & 10)} -> 358.08 | E63: {=INDIRECT("'" & E$40 & "'!B" & 10)} -> 1027.09 | F63: {=INDIRECT("'" & F$40 & "'!B" & 10)} -> 309.88 | G63: {=INDIRECT("'" & G$40 & "'!B" & 10)} -> 2048.56 | H63: {=INDIRECT("'" & H$40 & "'!B" & 10)} -> 4090.48 | I63: {=INDIRECT("'" & I$40 & "'!B" & 10)} -> 3675.54 | J63: {=INDIRECT("'" & J$40 & "'!B" & 10)} -> 4413.45 | ... N63: {=INDIRECT("'" & N$40 & "'!B" & 10)} -> 20649.4
B64: LE SOLDE | C64: {=INDIRECT("'" & C$40 & "'!B" & 14)} -> 358.08 | D64: {=INDIRECT("'" & D$40 & "'!B" & 14)} -> 1027.09 | E64: {=INDIRECT("'" & E$40 & "'!B" & 14)} -> 309.88 | F64: {=INDIRECT("'" & F$40 & "'!B" & 14)} -> 2048.56 | G64: {=INDIRECT("'" & G$40 & "'!B" & 14)} -> 4090.48 | H64: {=INDIRECT("'" & H$40 & "'!B" & 14)} -> 3675.54 | I64: {=INDIRECT("'" & I$40 & "'!B" & 14)} -> 3421.35 | J64: {=INDIRECT("'" & J$40 & "'!B" & 14)} -> 9532.22 | ... N64: {=INDIRECT("'" & N$40 & "'!B" & 14)} -> 21154.32
B65: OBJECTIF SOLDE | C65: {=INDIRECT("'" & C$58 & "'!N" & 14)} -> 0 | D65: {=INDIRECT("'" & D$58 & "'!N" & 14)} -> 0 | E65: {=INDIRECT("'" & E$58 & "'!N" & 14)} -> 0 | F65: {=INDIRECT("'" & F$58 & "'!N" & 14)} -> 0 | G65: {=INDIRECT("'" & G$58 & "'!N" & 14)} -> 0 | H65: {=INDIRECT("'" & H$58 & "'!N" & 14)} -> 0 | I65: {=INDIRECT("'" & I$58 & "'!N" & 14)} -> 0 | J65: {=INDIRECT("'" & J$58 & "'!N" & 14)} -> 0 | ... N65: {=INDIRECT("'" & N$58 & "'!N" & 14)} -> 0
B66: ECART SOLDE - OBJECTIF | C66: =C64-C65 -> 358.08 | D66: =D64-D65 -> 1027.09 | E66: =E64-E65 -> 309.88 | F66: =F64-F65 -> 2048.56 | G66: =G64-G65 -> 4090.48 | H66: =H64-H65 -> 3675.54 | I66: =I64-I65 -> 3421.35 | J66: =J64-J65 -> 9532.22 | ... N66: =N64-N65 -> 21154.32

Sheet Janvier
B1: TABLEAU MENSUEL
B2: ='TABLEAU ANNUEL'!B2 -> 2026
B3: {=_xlfn.TEXTAFTER(CELL("nomfichier",B3),"x]")} -> Janvier
F4: =UPPER(F23)
B5: REVENUS REEL TOTAL | H5: DEPENSE RÉELLE TOTALE | L5: SOLDE PRECEDENT
B6: =G24 -> 628.42 | H6: =SUM(G25:G29) -> 428.31 | L6: 157.97
B9: LE SOLDE BUDGETISE | H9: PREVISION ECONOMIE MENSUELLE (budget) | L9: OBJECTIF ECONOMIE MENSUELLE
B10: =L6+H10 -> 157.97 | H10: =E24-SUM(E25:F29) -> 0 | L10: 10
B13: LE SOLDE | H13: ECONOMIE MENSUELLE REALISE | L13: OBJECTIF SOLDE
B14: =B6+L6-H6 -> 358.08 | H14: =G30 -> 200.11 | L14: =L10+L6 -> 167.97
B22: RÉSUMÉ DE BUDGET | L22: Dépense
B23: SOURCE | E23: BUDGET | G23: RÉEL | H23: ECART | L23: SOURCE | M23: DATE | N23: LIBELLE | O23: RÉEL | P23: BUDGET | Q23: ECART
B24: REVENUS | E24: =F92 -> 0 | G24: =E92 -> 628.42 | H24: =G24-E24 -> 628.42 | L24: {=_xlfn._xlws.FILTER(_xlfn.CHOOSECOLS(Transaction[],2,1,3,7),(Transaction[Année]=$B$2)*(Transaction[MOIS]=$B$3)*(Transaction[Dépense/Revenue]=L22),"")} -> PAIEMENT CARTE | M24: 46045 | N24: Paiement par carte bancaire | O24: 51.85 | P24: =O24 -> 51.85 | Q24: =P24-O24 -> 0
B25: DEPENSE | E25: =P91 -> 0 | G25: =O92 -> 428.31 | H25: =G25-E25 -> 428.31 | L25: CHEQUE | M25: 46048 | N25: Chèque émis | O25: 54.89 | P25: =O25 -> 54.89 | Q25: =P25-O25 -> 0
L26: CHEQUE | M26: 46048 | N26: Chèque émis | O26: 131.1 | P26: =O26 -> 131.1 | Q26: =P26-O26 -> 0
L27: PAIEMENT EN LIGNE | M27: 46029 | N27: Paiement en ligne - sites divers | O27: 190.47 | P27: =O27 -> 190.47 | Q27: =P27-O27 -> 0
P28: =O28 -> 0 | Q28: =P28-O28 -> 0
P29: =O29 -> 0 | Q29: =P29-O29 -> 0
B30: MONTANTS RESTANT | E30: =E24-SUM(E25:F29) -> 0 | G30: =G24-SUM(G25:G29) -> 200.11 | H30: =H24-SUM(H25:I29) -> 200.11 | P30: =O30 -> 0 | Q30: =P30-O30 -> 0
P31: =O31 -> 0 | Q31: =P31-O31 -> 0
P32: =O32 -> 0 | Q32: =P32-O32 -> 0
P33: =O33 -> 0 | Q33: =P33-O33 -> 0
P34: =O34 -> 0 | Q34: =P34-O34 -> 0
P35: =O35 -> 0 | Q35: =P35-O35 -> 0
P36: =O36 -> 0 | Q36: =P36-O36 -> 0
B37: revenue | P37: =O37 -> 0 | Q37: =P37-O37 -> 0
B38: SOURCES | C38: DATE | D38: LIBELLE | E38: RÉEL | F38: BUDGET | H38: Écart | I38: DÉPOSÉ SUR | P38: =O38 -> 0 | Q38: =P38-O38 -> 0
B39: {=_xlfn._xlws.FILTER(_xlfn.CHOOSECOLS(Transaction[],2,1,3,7),(Transaction[Année]=$B$2)*(Transaction[MOIS]=$B$3)*(Transaction[Dépense/Revenue]=B37),"")} -> PAIEMENT EN LIGNE | C39: 46031 | D39: Paiement en ligne - sites divers | E39: 628.42 | H39: =E39-F39 -> 628.42 | P39: =O39 -> 0 | Q39: =P39-O39 -> 0
F40: 0 | H40: =E40-F40 -> 0 | P40: =O40 -> 0 | Q40: =P40-O40 -> 0
F41: 0 | H41: =E41-F41 -> 0 | P41: =O41 -> 0 | Q41: =P41-O41 -> 0
F42: =E42 -> 0 | H42: =E42-F42 -> 0 | P42: =O42 -> 0 | Q42: =P42-O42 -> 0
F43: =E43 -> 0 | H43: =E43-F43 -> 0 | P43: =O43 -> 0 | Q43: =P43-O43 -> 0
F44: =E44 -> 0 | H44: =E44-F44 -> 0 | P44: =O44 -> 0 | Q44: =P44-O44 -> 0
F45: =E45 -> 0 | H45: =E45-F45 -> 0 | P45: =O45 -> 0 | Q45: =P45-O45 -> 0
F46: =E46 -> 0 | H46: =E46-F46 -> 0 | P46: =O46 -> 0 | Q46: =P46-O46 -> 0
F47: =E47 -> 0 | H47: =E47-F47 -> 0 | P47: =O47 -> 0 | Q47: =P47-O47 -> 0
F48: =E48 -> 0 | H48: =E48-F48 -> 0 | P48: =O48 -> 0 | Q48: =P48-O48 -> 0
F49: =E49 -> 0 | H49: =E49-F49 -> 0 | P49: =O49 -> 0 | Q49: =P49-O49 -> 0
F50: =E50 -> 0 | H50: =E50-F50 -> 0 | P50: =O50 -> 0 | Q50: =P50-O50 -> 0
F51: =E51 -> 0 | H51: =E51-F51 -> 0 | P51: =O51 -> 0 | Q51: =P51-O51 -> 0
F52: =E52 -> 0 | H52: =E52-F52 -> 0 | P52: =O52 -> 0 | Q52: =P52-O52 -> 0
F53: =E53 -> 0 | H53: =E53-F53 -> 0 | P53: =O53 -> 0 | Q53: =P53-O53 -> 0
... F91: =E91 -> 0 | H91: =E91-F91 -> 0 | P91: =O91 -> 0 | Q91: =P91-O91 -> 0
B92: TOTAL | E92: =SUM(E39:E91) -> 628.42 | F92: =SUM(F39:G91) -> 0 | H92: =E92-F92 -> 628.42 | L92: TOTAL | O92: =SUM(O24:O91) -> 428.31 | P92: =SUM(P24:P91) -> 428.31 | Q92: =O92-P92 -> 0

Sheet Février
B1: TABLEAU MENSUEL
B2: ='TABLEAU ANNUEL'!B2 -> 2026
B3: {=_xlfn.TEXTAFTER(CELL("nomfichier",B3),"x]")} -> Février
F4: =UPPER(F23)
B5: REVENUS REEL TOTAL | H5: DEPENSE RÉELLE TOTALE | L5: SOLDE PRECEDENT
B6: =G24 -> 1154.22 | H6: =SUM(G25:G29) -> 485.21 | L6: =Janvier!B14 -> 358.08
B9: LE SOLDE BUDGETISE | H9: PREVISION ECONOMIE MENSUELLE (budget) | L9: OBJECTIF ECONOMIE MENSUELLE
B10: =L6+H10 -> 358.08 | H10: =E24-SUM(E25:F29) -> 0 | L10: 10
B13: LE SOLDE | H13: ECONOMIE MENSUELLE REALISE | L13: OBJECTIF SOLDE
B14: =B6+L6-H6 -> 1027.09 | H14: =G30 -> 669.01 | L14: =L10+L6 -> 368.08
B22: RÉSUMÉ DE BUDGET | L22: Dépense
B23: SOURCE | E23: BUDGET | G23: RÉEL | H23: ECART | L23: SOURCE | M23: DATE | N23: LIBELLE | O23: RÉEL | P23: BUDGET | Q23: ECART
B24: REVENUS | E24: =F92 -> 0 | G24: =E92 -> 1154.22 | H24: =G24-E24 -> 1154.22 | L24: {=_xlfn._xlws.FILTER(_xlfn.CHOOSECOLS(Transaction[],2,1,3,7),(Transaction[Année]=$B$2)*(Transaction[MOIS]=$B$3)*(Transaction[Dépense/Revenue]=L22),"")} -> REMBOURSEMENT PRET | M24: 46075 | N24: Remboursement prêt immobilier | O24: 61.71 | P24: =O24 -> 61.71 | Q24: =P24-O24 -> 0
B25: DEPENSE | E25: =P91 -> 0 | G25: =O92 -> 485.21 | H25: =G25-E25 -> 485.21 | L25: RETRAIT DAB | M25: 46059 | N25: Retrait au distributeur automatique | O25: 84.48 | P25: =O25 -> 84.48 | Q25: =P25-O25 -> 0
L26: RESTAURANT | M26: 46073 | N26: Restaurant Le Bistro Parisien | O26: 93.95 | P26: =O26 -> 93.95 | Q26: =P26-O26 -> 0
L27: TRANSPORT | M27: 46058 | N27: Abonnement transports RATP | O27: 112.1 | P27: =O27 -> 112.1 | Q27: =P27-O27 -> 0
L28: PAIEMENT GOOGLE | M28: 46062 | N28: Paiement Google Play Store | O28: 132.97 | P28: =O28 -> 132.97 | Q28: =P28-O28 -> 0
P29: =O29 -> 0 | Q29: =P29-O29 -> 0
B30: MONTANTS RESTANT | E30: =E24-SUM(E25:F29) -> 0 | G30: =G24-SUM(G25:G29) -> 669.01 | H30: =H24-SUM(H25:I29) -> 669.01 | P30: =O30 -> 0 | Q30: =P30-O30 -> 0
P31: =O31 -> 0 | Q31: =P31-O31 -> 0
P32: =O32 -> 0 | Q32: =P32-O32 -> 0
P33: =O33 -> 0 | Q33: =P33-O33 -> 0
P34: =O34 -> 0 | Q34: =P34-O34 -> 0
P35: =O35 -> 0 | Q35: =P35-O35 -> 0
P36: =O36 -> 0 | Q36: =P36-O36 -> 0
B37: revenue | P37: =O37 -> 0 | Q37: =P37-O37 -> 0
B38: SOURCES | C38: DATE | D38: LIBELLE | E38: RÉEL | F38: BUDGET | H38: Écart | I38: DÉPOSÉ SUR | P38: =O38 -> 0 | Q38: =P38-O38 -> 0
B39: {=_xlfn._xlws.FILTER(_xlfn.CHOOSECOLS(Transaction[],2,1,3,7),(Transaction[Année]=$B$2)*(Transaction[MOIS]=$B$3)*(Transaction[Dépense/Revenue]=B37),"")} -> ASSURANCE AUTO | C39: 46070 | D39: Prélèvement assurance automobile | E39: 1154.22 | F39: =0 -> 0 | H39: =E39-F39 -> 1154.22 | P39: =O39 -> 0 | Q39: =P39-O39 -> 0
F40: 0 | H40: =E40-F40 -> 0 | P40: =O40 -> 0 | Q40: =P40-O40 -> 0
F41: 0 | H41: =E41-F41 -> 0 | P41: =O41 -> 0 | Q41: =P41-O41 -> 0
F42: =E42 -> 0 | H42: =E42-F42 -> 0 | P42: =O42 -> 0 | Q42: =P42-O42 -> 0
F43: =E43 -> 0 | H43: =E43-F43 -> 0 | P43: =O43 -> 0 | Q43: =P43-O43 -> 0
F44: =E44 -> 0 | H44: =E44-F44 -> 0 | P44: =O44 -> 0 | Q44: =P44-O44 -> 0
F45: =E45 -> 0 | H45: =E45-F45 -> 0 | P45: =O45 -> 0 | Q45: =P45-O45 -> 0
F46: =E46 -> 0 | H46: =E46-F46 -> 0 | P46: =O46 -> 0 | Q46: =P46-O46 -> 0
F47: =E47 -> 0 | H47: =E47-F47 -> 0 | P47: =O47 -> 0 | Q47: =P47-O47 -> 0
F48: =E48 -> 0 | H48: =E48-F48 -> 0 | P48: =O48 -> 0 | Q48: =P48-O48 -> 0
F49: =E49 -> 0 | H49: =E49-F49 -> 0 | P49: =O49 -> 0 | Q49: =P49-O49 -> 0
F50: =E50 -> 0 | H50: =E50-F50 -> 0 | P50: =O50 -> 0 | Q50: =P50-O50 -> 0
F51: =E51 -> 0 | H51: =E51-F51 -> 0 | P51: =O51 -> 0 | Q51: =P51-O51 -> 0
F52: =E52 -> 0 | H52: =E52-F52 -> 0 | P52: =O52 -> 0 | Q52: =P52-O52 -> 0
F53: =E53 -> 0 | H53: =E53-F53 -> 0 | P53: =O53 -> 0 | Q53: =P53-O53 -> 0
... F91: =E91 -> 0 | H91: =E91-F91 -> 0 | P91: =O91 -> 0 | Q91: =P91-O91 -> 0
B92: TOTAL | E92: =SUM(E39:E91) -> 1154.22 | F92: =SUM(F39:G91) -> 0 | H92: =E92-F92 -> 1154.22 | L92: TOTAL | O92: =SUM(O24:O91) -> 485.21 | P92: =SUM(P24:P91) -> 485.21 | Q92: =O92-P92 -> 0

Sheet Mars
B1: TABLEAU MENSUEL
B2: ='TABLEAU ANNUEL'!B2 -> 2026
B3: {=_xlfn.TEXTAFTER(CELL("nomfichier",B3),"x]")} -> Mars
F4: =UPPER(F23)
B5: REVENUS REEL TOTAL | H5: DEPENSE RÉELLE TOTALE | L5: SOLDE PRECEDENT
B6: =G24 -> 0 | H6: =SUM(G25:G29) -> 717.21 | L6: =Février!B14 -> 1027.09
B9: LE SOLDE BUDGETISE | H9: PREVISION ECONOMIE MENSUELLE (budget) | L9: OBJECTIF ECONOMIE MENSUELLE
B10: =L6+H10 -> 1027.09 | H10: =E24-SUM(E25:F29) -> 0 | L10: 10
B13: LE SOLDE | H13: ECONOMIE MENSUELLE REALISE | L13: OBJECTIF SOLDE
B14: =B6+L6-H6 -> 309.88 | H14: =G30 -> -717.21 | L14: =L10+L6 -> 1037.09
B22: RÉSUMÉ DE BUDGET | L22: Dépense
B23: SOURCE | E23: BUDGET | G23: RÉEL | H23: ECART | L23: SOURCE | M23: DATE | N23: LIBELLE | O23: RÉEL | P23: BUDGET | Q23: ECART
B24: REVENUS | E24: =F92 -> 0 | G24: =E92 -> 0 | H24: =G24-E24 -> 0 | L24: {=_xlfn._xlws.FILTER(_xlfn.CHOOSECOLS(Transaction[],2,1,3,7),(Transaction[Année]=$B$2)*(Transaction[MOIS]=$B$3)*(Transaction[Dépense/Revenue]=L22),"")} -> ASSURANCE AUTO | M24: 46094 | N24: Prélèvement assurance automobile | O24: 12.69 | P24: =O24 -> 12.69 | Q24: =P24-O24 -> 0
B25: DEPENSE | E25: =P91 -> 0 | G25: =O92 -> 717.21 | H25: =G25-E25 -> 717.21 | L25: TRANSPORT | M25: 46109 | N25: Abonnement transports RATP | O25: 61.18 | P25: =O25 -> 61.18 | Q25: =P25-O25 -> 0
L26: STATION ESSENCE | M26: 46096 | N26: Station Total - carburant | O26: 104.98 | P26: =O26 -> 104.98 | Q26: =P26-O26 -> 0
L27: RETRAIT DAB | M27: 46101 | N27: Retrait au distributeur automatique | O27: 106.58 | P27: =O27 -> 106.58 | Q27: =P27-O27 -> 0
L28: REMBOURSEMENT PRET | M28: 46092 | N28: Remboursement prêt immobilier | O28: 133.11 | P28: =O28 -> 133.11 | Q28: =P28-O28 -> 0
L29: BON CADEAUX | M29: 46103 | N29: Carte cadeau Fnac | O29: 144.53 | P29: =O29 -> 144.53 | Q29: =P29-O29 -> 0
B30: MONTANTS RESTANT | E30: =E24-SUM(E25:F29) -> 0 | G30: =G24-SUM(G25:G29) -> -717.21 | H30: =H24-SUM(H25:I29) -> -717.21 | L30: CHEQUE | M30: 46105 | N30: Chèque émis | O30: 154.14 | P30: =O30 -> 154.14 | Q30: =P30-O30 -> 0
P31: =O31 -> 0 | Q31: =P31-O31 -> 0
P32: =O32 -> 0 | Q32: =P32-O32 -> 0
P33: =O33 -> 0 | Q33: =P33-O33 -> 0
P34: =O34 -> 0 | Q34: =P34-O34 -> 0
P35: =O35 -> 0 | Q35: =P35-O35 -> 0
P36: =O36 -> 0 | Q36: =P36-O36 -> 0
B37: revenue | P37: =O37 -> 0 | Q37: =P37-O37 -> 0
B38: SOURCES | C38: DATE | D38: LIBELLE | E38: RÉEL | F38: BUDGET | H38: Écart | I38: DÉPOSÉ SUR | P38: =O38 -> 0 | Q38: =P38-O38 -> 0
B39: {=_xlfn._xlws.FILTER(_xlfn.CHOOSECOLS(Transaction[],2,1,3,7),(Transaction[Année]=$B$2)*(Transaction[MOIS]=$B$3)*(Transaction[Dépense/Revenue]=B37),"")} | F39: =0 -> 0 | H39: =E39-F39 -> 0 | P39: =O39 -> 0 | Q39: =P39-O39 -> 0
F40: 0 | H40: =E40-F40 -> 0 | P40: =O40 -> 0 | Q40: =P40-O40 -> 0
F41: 0 | H41: =E41-F41 -> 0 | P41: =O41 -> 0 | Q41: =P41-O41 -> 0
F42: =E42 -> 0 | H42: =E42-F42 -> 0 | P42: =O42 -> 0 | Q42: =P42-O42 -> 0
F43: =E43 -> 0 | H43: =E43-F43 -> 0 | P43: =O43 -> 0 | Q43: =P43-O43 -> 0
F44: =E44 -> 0 | H44: =E44-F44 -> 0 | P44: =O44 -> 0 | Q44: =P44-O44 -> 0
F45: =E45 -> 0 | H45: =E45-F45 -> 0 | P45: =O45 -> 0 | Q45: =P45-O45 -> 0
F46: =E46 -> 0 | H46: =E46-F46 -> 0 | P46: =O46 -> 0 | Q46: =P46-O46 -> 0
F47: =E47 -> 0 | H47: =E47-F47 -> 0 | P47: =O47 -> 0 | Q47: =P47-O47 -> 0
F48: =E48 -> 0 | H48: =E48-F48 -> 0 | P48: =O48 -> 0 | Q48: =P48-O48 -> 0
F49: =E49 -> 0 | H49: =E49-F49 -> 0 | P49: =O49 -> 0 | Q49: =P49-O49 -> 0
F50: =E50 -> 0 | H50: =E50-F50 -> 0 | P50: =O50 -> 0 | Q50: =P50-O50 -> 0
F51: =E51 -> 0 | H51: =E51-F51 -> 0 | P51: =O51 -> 0 | Q51: =P51-O51 -> 0
F52: =E52 -> 0 | H52: =E52-F52 -> 0 | P52: =O52 -> 0 | Q52: =P52-O52 -> 0
F53: =E53 -> 0 | H53: =E53-F53 -> 0 | P53: =O53 -> 0 | Q53: =P53-O53 -> 0
... F91: =E91 -> 0 | H91: =E91-F91 -> 0 | P91: =O91 -> 0 | Q91: =P91-O91 -> 0
B92: TOTAL | E92: =SUM(E39:E91) -> 0 | F92: =SUM(F39:G91) -> 0 | H92: =E92-F92 -> 0 | L92: TOTAL | O92: =SUM(O24:O91) -> 717.21 | P92: =SUM(P24:P91) -> 717.21 | Q92: =O92-P92 -> 0

Sheet Avril
B1: TABLEAU MENSUEL
B2: ='TABLEAU ANNUEL'!B2 -> 2026
B3: {=_xlfn.TEXTAFTER(CELL("nomfichier",B3),"x]")} -> Avril
F4: =UPPER(F23)
B5: REVENUS REEL TOTAL | H5: DEPENSE RÉELLE TOTALE | L5: SOLDE PRECEDENT
B6: =G24 -> 2194.19 | H6: =SUM(G25:G29) -> 455.51 | L6: =Mars!B14 -> 309.88
B9: LE SOLDE BUDGETISE | H9: PREVISION ECONOMIE MENSUELLE (budget) | L9: OBJECTIF ECONOMIE MENSUELLE
B10: =L6+H10 -> 309.88 | H10: =E24-SUM(E25:F29) -> 0 | L10: 10
B13: LE SOLDE | H13: ECONOMIE MENSUELLE REALISE | L13: OBJECTIF SOLDE
B14: =B6+L6-H6 -> 2048.56 | H14: =G30 -> 1738.68 | L14: =L10+L6 -> 319.88
B22: RÉSUMÉ DE BUDGET | L22: Dépense
B23: SOURCE | E23: BUDGET | G23: RÉEL | H23: ECART | L23: SOURCE | M23: DATE | N23: LIBELLE | O23: RÉEL | P23: BUDGET | Q23: ECART
B24: REVENUS | E24: =F92 -> 0 | G24: =E92 -> 2194.19 | H24: =G24-E24 -> 2194.19 | L24: {=_xlfn._xlws.FILTER(_xlfn.CHOOSECOLS(Transaction[],2,1,3,7),(Transaction[Année]=$B$2)*(Transaction[MOIS]=$B$3)*(Transaction[Dépense/Revenue]=L22),"")} -> FACTURE TELEPHONE | M24: 46124 | N24: Paiement facture téléphonique SFR | O24: 25.99 | P24: =O24 -> 25.99 | Q24: =P24-O24 -> 0
B25: DEPENSE | E25: =P91 -> 0 | G25: =O92 -> 455.51 | H25: =G25-E25 -> 455.51 | L25: PAIEMENT EN LIGNE | M25: 46121 | N25: Paiement en ligne - sites divers | O25: 30.83 | P25: =O25 -> 30.83 | Q25: =P25-O25 -> 0
L26: VIREMENT EMIS | M26: 46124 | N26: Virement émis vers compte épargne | O26: 67.79 | P26: =O26 -> 67.79 | Q26: =P26-O26 -> 0
L27: FACTURE TELEPHONE | M27: 46127 | N27: Paiement facture téléphonique SFR | O27: 132.87 | P27: =O27 -> 132.87 | Q27: =P27-O27 -> 0
L28: COURSES | M28: 46113 | N28: Courses alimentaires Carrefour | O28: 198.03 | P28: =O28 -> 198.03 | Q28: =P28-O28 -> 0
P29: =O29 -> 0 | Q29: =P29-O29 -> 0
B30: MONTANTS RESTANT | E30: =E24-SUM(E25:F29) -> 0 | G30: =G24-SUM(G25:G29) -> 1738.68 | H30: =H24-SUM(H25:I29) -> 1738.68 | P30: =O30 -> 0 | Q30: =P30-O30 -> 0
P31: =O31 -> 0 | Q31: =P31-O31 -> 0
P32: =O32 -> 0 | Q32: =P32-O32 -> 0
P33: =O33 -> 0 | Q33: =P33-O33 -> 0
P34: =O34 -> 0 | Q34: =P34-O34 -> 0
P35: =O35 -> 0 | Q35: =P35-O35 -> 0
P36: =O36 -> 0 | Q36: =P36-O36 -> 0
B37: revenue | P37: =O37 -> 0 | Q37: =P37-O37 -> 0
B38: SOURCES | C38: DATE | D38: LIBELLE | E38: RÉEL | F38: BUDGET | H38: Écart | I38: DÉPOSÉ SUR | P38: =O38 -> 0 | Q38: =P38-O38 -> 0
B39: {=_xlfn._xlws.FILTER(_xlfn.CHOOSECOLS(Transaction[],2,1,3,7),(Transaction[Année]=$B$2)*(Transaction[MOIS]=$B$3)*(Transaction[Dépense/Revenue]=B37),"")} -> PHARMACIE | C39: 46126 | D39: Achat pharmacie | E39: 2194.19 | F39: =0 -> 0 | H39: =E39-F39 -> 2194.19 | P39: =O39 -> 0 | Q39: =P39-O39 -> 0
F40: 0 | H40: =E40-F40 -> 0 | P40: =O40 -> 0 | Q40: =P40-O40 -> 0
F41: 0 | H41: =E41-F41 -> 0 | P41: =O41 -> 0 | Q41: =P41-O41 -> 0
F42: =E42 -> 0 | H42: =E42-F42 -> 0 | P42: =O42 -> 0 | Q42: =P42-O42 -> 0
F43: =E43 -> 0 | H43: =E43-F43 -> 0 | P43: =O43 -> 0 | Q43: =P43-O43 -> 0
F44: =E44 -> 0 | H44: =E44-F44 -> 0 | P44: =O44 -> 0 | Q44: =P44-O44 -> 0
F45: =E45 -> 0 | H45: =E45-F45 -> 0 | P45: =O45 -> 0 | Q45: =P45-O45 -> 0
F46: =E46 -> 0 | H46: =E46-F46 -> 0 | P46: =O46 -> 0 | Q46: =P46-O46 -> 0
F47: =E47 -> 0 | H47: =E47-F47 -> 0 | P47: =O47 -> 0 | Q47: =P47-O47 -> 0
F48: =E48 -> 0 | H48: =E48-F48 -> 0 | P48: =O48 -> 0 | Q48: =P48-O48 -> 0
F49: =E49 -> 0 | H49: =E49-F49 -> 0 | P49: =O49 -> 0 | Q49: =P49-O49 -> 0
F50: =E50 -> 0 | H50: =E50-F50 -> 0 | P50: =O50 -> 0 | Q50: =P50-O50 -> 0
F51: =E51 -> 0 | H51: =E51-F51 -> 0 | P51: =O51 -> 0 | Q51: =P51-O51 -> 0
F52: =E52 -> 0 | H52: =E52-F52 -> 0 | P52: =O52 -> 0 | Q52: =P52-O52 -> 0
F53: =E53 -> 0 | H53: =E53-F53 -> 0 | P53: =O53 -> 0 | Q53: =P53-O53 -> 0
... F91: =E91 -> 0 | H91: =E91-F91 -> 0 | P91: =O91 -> 0 | Q91: =P91-O91 -> 0
B92: TOTAL | E92: =SUM(E39:E91) -> 2194.19 | F92: =SUM(F39:G91) -> 0 | H92: =E92-F92 -> 2194.19 | L92: TOTAL | O92: =SUM(O24:O91) -> 455.51 | P92: =SUM(P24:P91) -> 455.51 | Q92: =O92-P92 -> 0

Sheet Mai
B1: TABLEAU MENSUEL
B2: ='TABLEAU ANNUEL'!B2 -> 2026
B3: {=_xlfn.TEXTAFTER(CELL("nomfichier",B3),"x]")} -> Mai
F4: =UPPER(F23)
B5: REVENUS REEL TOTAL | H5: DEPENSE RÉELLE TOTALE | L5: SOLDE PRECEDENT
B6: =G24 -> 2611.62 | H6: =SUM(G25:G29) -> 569.7 | L6: =Avril!B14 -> 2048.56
B9: LE SOLDE BUDGETISE | H9: PREVISION ECONOMIE MENSUELLE (budget) | L9: OBJECTIF ECONOMIE MENSUELLE
B10: =L6+H10 -> 2048.56 | H10: =E24-SUM(E25:F29) -> 0 | L10: 10
B13: LE SOLDE | H13: ECONOMIE MENSUELLE REALISE | L13: OBJECTIF SOLDE
B14: =B6+L6-H6 -> 4090.48 | H14: =G30 -> 2041.92 | L14: =L10+L6 -> 2058.56
B22: RÉSUMÉ DE BUDGET | L22: Dépense
B23: SOURCE | E23: BUDGET | G23: RÉEL | H23: ECART | L23: SOURCE | M23: DATE | N23: LIBELLE | O23: RÉEL | P23: BUDGET | Q23: ECART
B24: REVENUS | E24: =F92 -> 0 | G24: =E92 -> 2611.62 | H24: =G24-E24 -> 2611.62 | L24: {=_xlfn._xlws.FILTER(_xlfn.CHOOSECOLS(Transaction[],2,1,3,7),(Transaction[Année]=$B$2)*(Transaction[MOIS]=$B$3)*(Transaction[Dépense/Revenue]=L22),"")} -> TRANSPORT | M24: 46172 | N24: Abonnement transports RATP | O24: 17.27 | P24: =O24 -> 17.27 | Q24: =P24-O24 -> 0
B25: DEPENSE | E25: =P91 -> 0 | G25: =O92 -> 569.7 | H25: =G25-E25 -> 569.7 | L25: RETRAIT DAB | M25: 46151 | N25: Retrait au distributeur automatique | O25: 28.73 | P25: =O25 -> 28.73 | Q25: =P25-O25 -> 0
L26: CINEMA | M26: 46146 | N26: Place de cinéma UGC | O26: 59.03 | P26: =O26 -> 59.03 | Q26: =P26-O26 -> 0
L27: REMUNERATION | M27: 46162 | N27: Salaire - Société ABC | O27: 74.36 | P27: =O27 -> 74.36 | Q27: =P27-O27 -> 0
L28: FACTURE TELEPHONE | M28: 46172 | N28: Paiement facture téléphonique SFR | O28: 78.98 | P28: =O28 -> 78.98 | Q28: =P28-O28 -> 0
L29: PAIEMENT CARTE | M29: 46169 | N29: Paiement par carte bancaire | O29: 113.12 | P29: =O29 -> 113.12 | Q29: =P29-O29 -> 0
B30: MONTANTS RESTANT | E30: =E24-SUM(E25:F29) -> 0 | G30: =G24-SUM(G25:G29) -> 2041.92 | H30: =H24-SUM(H25:I29) -> 2041.92 | L30: RESTAURANT | M30: 46164 | N30: Restaurant Le Bistro Parisien | O30: 198.21 | P30: =O30 -> 198.21 | Q30: =P30-O30 -> 0
P31: =O31 -> 0 | Q31: =P31-O31 -> 0
P32: =O32 -> 0 | Q32: =P32-O32 -> 0
P33: =O33 -> 0 | Q33: =P33-O33 -> 0
P34: =O34 -> 0 | Q34: =P34-O34 -> 0
P35: =O35 -> 0 | Q35: =P35-O35 -> 0
P36: =O36 -> 0 | Q36: =P36-O36 -> 0
B37: revenue | P37: =O37 -> 0 | Q37: =P37-O37 -> 0
B38: SOURCES | C38: DATE | D38: LIBELLE | E38: RÉEL | F38: BUDGET | H38: Écart | I38: DÉPOSÉ SUR | P38: =O38 -> 0 | Q38: =P38-O38 -> 0
B39: {=_xlfn._xlws.FILTER(_xlfn.CHOOSECOLS(Transaction[],2,1,3,7),(Transaction[Année]=$B$2)*(Transaction[MOIS]=$B$3)*(Transaction[Dépense/Revenue]=B37),"")} -> BON CADEAUX | C39: 46151 | D39: Carte cadeau Fnac | E39: 2611.62 | F39: =0 -> 0 | H39: =E39-F39 -> 2611.62 | P39: =O39 -> 0 | Q39: =P39-O39 -> 0
F40: 0 | H40: =E40-F40 -> 0 | P40: =O40 -> 0 | Q40: =P40-O40 -> 0
F41: 0 | H41: =E41-F41 -> 0 | P41: =O41 -> 0 | Q41: =P41-O41 -> 0
F42: =E42 -> 0 | H42: =E42-F42 -> 0 | P42: =O42 -> 0 | Q42: =P42-O42 -> 0
F43: =E43 -> 0 | H43: =E43-F43 -> 0 | P43: =O43 -> 0 | Q43: =P43-O43 -> 0
F44: =E44 -> 0 | H44: =E44-F44 -> 0 | P44: =O44 -> 0 | Q44: =P44-O44 -> 0
F45: =E45 -> 0 | H45: =E45-F45 -> 0 | P45: =O45 -> 0 | Q45: =P45-O45 -> 0
F46: =E46 -> 0 | H46: =E46-F46 -> 0 | P46: =O46 -> 0 | Q46: =P46-O46 -> 0
F47: =E47 -> 0 | H47: =E47-F47 -> 0 | P47: =O47 -> 0 | Q47: =P47-O47 -> 0
F48: =E48 -> 0 | H48: =E48-F48 -> 0 | P48: =O48 -> 0 | Q48: =P48-O48 -> 0
F49: =E49 -> 0 | H49: =E49-F49 -> 0 | P49: =O49 -> 0 | Q49: =P49-O49 -> 0
F50: =E50 -> 0 | H50: =E50-F50 -> 0 | P50: =O50 -> 0 | Q50: =P50-O50 -> 0
F51: =E51 -> 0 | H51: =E51-F51 -> 0 | P51: =O51 -> 0 | Q51: =P51-O51 -> 0
F52: =E52 -> 0 | H52: =E52-F52 -> 0 | P52: =O52 -> 0 | Q52: =P52-O52 -> 0
F53: =E53 -> 0 | H53: =E53-F53 -> 0 | P53: =O53 -> 0 | Q53: =P53-O53 -> 0
... F91: =E91 -> 0 | H91: =E91-F91 -> 0 | P91: =O91 -> 0 | Q91: =P91-O91 -> 0
B92: TOTAL | E92: =SUM(E39:E91) -> 2611.62 | F92: =SUM(F39:G91) -> 0 | H92: =E92-F92 -> 2611.62 | L92: TOTAL | O92: =SUM(O24:O91) -> 569.7 | P92: =SUM(P24:P91) -> 569.7 | Q92: =O92-P92 -> 0

Sheet Juin
B1: TABLEAU MENSUEL
B2: ='TABLEAU ANNUEL'!B2 -> 2026
B3: {=_xlfn.TEXTAFTER(CELL("nomfichier",B3),"x]")} -> Juin
F4: =UPPER(F23)
B5: REVENUS REEL TOTAL | H5: DEPENSE RÉELLE TOTALE | L5: SOLDE PRECEDENT
B6: =G24 -> 693.57 | H6: =SUM(G25:G29) -> 1108.51 | L6: =Mai!B14 -> 4090.48
B9: LE SOLDE BUDGETISE | H9: PREVISION ECONOMIE MENSUELLE (budget) | L9: OBJECTIF ECONOMIE MENSUELLE
B10: =L6+H10 -> 4090.48 | H10: =E24-SUM(E25:F29) -> 0 | L10: 10
B13: LE SOLDE | H13: ECONOMIE MENSUELLE REALISE | L13: OBJECTIF SOLDE
B14: =B6+L6-H6 -> 3675.54 | H14: =G30 -> -414.94 | L14: =L10+L6 -> 4100.48
B22: RÉSUMÉ DE BUDGET | L22: Dépense
B23: SOURCE | E23: BUDGET | G23: RÉEL | H23: ECART | L23: SOURCE | M23: DATE | N23: LIBELLE | O23: RÉEL | P23: BUDGET | Q23: ECART
B24: REVENUS | E24: =F92 -> 0 | G24: =E92 -> 693.57 | H24: =G24-E24 -> 693.57 | L24: {=_xlfn._xlws.FILTER(_xlfn.CHOOSECOLS(Transaction[],2,1,3,7),(Transaction[Année]=$B$2)*(Transaction[MOIS]=$B$3)*(Transaction[Dépense/Revenue]=L22),"")} -> VIREMENT EMIS | M24: 46190 | N24: Virement émis vers compte épargne | O24: 32.37 | P24: =O24 -> 32.37 | Q24: =P24-O24 -> 0
B25: DEPENSE | E25: =P91 -> 0 | G25: =O92 -> 1108.51 | H25: =G25-E25 -> 1108.51 | L25: PAIEMENT GOOGLE | M25: 46192 | N25: Paiement Google Play Store | O25: 33.04 | P25: =O25 -> 33.04 | Q25: =P25-O25 -> 0
L26: PAIEMENT EN LIGNE | M26: 46200 | N26: Paiement en ligne - sites divers | O26: 70.39 | P26: =O26 -> 70.39 | Q26: =P26-O26 -> 0
L27: ASSURANCE AUTO | M27: 46174 | N27: Prélèvement assurance automobile | O27: 72.02 | P27: =O27 -> 72.02 | Q27: =P27-O27 -> 0
L28: PAIEMENT CARTE | M28: 46180 | N28: Paiement par carte bancaire | O28: 89.75 | P28: =O28 -> 89.75 | Q28: =P28-O28 -> 0
L29: REMUNERATION | M29: 46178 | N29: Salaire - Société ABC | O29: 107.15 | P29: =O29 -> 107.15 | Q29: =P29-O29 -> 0
B30: MONTANTS RESTANT | E30: =E24-SUM(E25:F29) -> 0 | G30: =G24-SUM(G25:G29) -> -414.94 | H30: =H24-SUM(H25:I29) -> -414.94 | L30: COURSES | M30: 46188 | N30: Courses alimentaires Carrefour | O30: 108.25 | P30: =O30 -> 108.25 | Q30: =P30-O30 -> 0
L31: FRAIS BANCAIRES | M31: 46195 | N31: Frais de tenue de compte mensuels | O31: 115.9 | P31: =O31 -> 115.9 | Q31: =P31-O31 -> 0
L32: COURSES | M32: 46190 | N32: Courses alimentaires Carrefour | O32: 127.26 | P32: =O32 -> 127.26 | Q32: =P32-O32 -> 0
L33: REMUNERATION | M33: 46174 | N33: Salaire - Société ABC | O33: 158.61 | P33: =O33 -> 158.61 | Q33: =P33-O33 -> 0
L34: FRAIS BANCAIRES | M34: 46179 | N34: Frais de tenue de compte mensuels | O34: 193.77 | P34: =O34 -> 193.77 | Q34: =P34-O34 -> 0
P35: =O35 -> 0 | Q35: =P35-O35 -> 0
P36: =O36 -> 0 | Q36: =P36-O36 -> 0
B37: revenue | P37: =O37 -> 0 | Q37: =P37-O37 -> 0
B38: SOURCES | C38: DATE | D38: LIBELLE | E38: RÉEL | F38: BUDGET | H38: Écart | I38: DÉPOSÉ SUR | P38: =O38 -> 0 | Q38: =P38-O38 -> 0
B39: {=_xlfn._xlws.FILTER(_xlfn.CHOOSECOLS(Transaction[],2,1,3,7),(Transaction[Année]=$B$2)*(Transaction[MOIS]=$B$3)*(Transaction[Dépense/Revenue]=B37),"")} -> RETRAIT DAB | C39: 46182 | D39: Retrait au distributeur automatique | E39: 693.57 | F39: =0 -> 0 | H39: =E39-F39 -> 693.57 | P39: =O39 -> 0 | Q39: =P39-O39 -> 0
F40: 0 | H40: =E40-F40 -> 0 | P40: =O40 -> 0 | Q40: =P40-O40 -> 0
F41: 0 | H41: =E41-F41 -> 0 | P41: =O41 -> 0 | Q41: =P41-O41 -> 0
F42: =E42 -> 0 | H42: =E42-F42 -> 0 | P42: =O42 -> 0 | Q42: =P42-O42 -> 0
F43: =E43 -> 0 | H43: =E43-F43 -> 0 | P43: =O43 -> 0 | Q43: =P43-O43 -> 0
F44: =E44 -> 0 | H44: =E44-F44 -> 0 | P44: =O44 -> 0 | Q44: =P44-O44 -> 0
F45: =E45 -> 0 | H45: =E45-F45 -> 0 | P45: =O45 -> 0 | Q45: =P45-O45 -> 0
F46: =E46 -> 0 | H46: =E46-F46 -> 0 | P46: =O46 -> 0 | Q46: =P46-O46 -> 0
F47: =E47 -> 0 | H47: =E47-F47 -> 0 | P47: =O47 -> 0 | Q47: =P47-O47 -> 0
F48: =E48 -> 0 | H48: =E48-F48 -> 0 | P48: =O48 -> 0 | Q48: =P48-O48 -> 0
F49: =E49 -> 0 | H49: =E49-F49 -> 0 | P49: =O49 -> 0 | Q49: =P49-O49 -> 0
F50: =E50 -> 0 | H50: =E50-F50 -> 0 | P50: =O50 -> 0 | Q50: =P50-O50 -> 0
F51: =E51 -> 0 | H51: =E51-F51 -> 0 | P51: =O51 -> 0 | Q51: =P51-O51 -> 0
F52: =E52 -> 0 | H52: =E52-F52 -> 0 | P52: =O52 -> 0 | Q52: =P52-O52 -> 0
F53: =E53 -> 0 | H53: =E53-F53 -> 0 | P53: =O53 -> 0 | Q53: =P53-O53 -> 0
... F91: =E91 -> 0 | H91: =E91-F91 -> 0 | P91: =O91 -> 0 | Q91: =P91-O91 -> 0
B92: TOTAL | E92: =SUM(E39:E91) -> 693.57 | F92: =SUM(F39:G91) -> 0 | H92: =E92-F92 -> 693.57 | L92: TOTAL | O92: =SUM(O24:O91) -> 1108.51 | P92: =SUM(P24:P91) -> 1108.51 | Q92: =O92-P92 -> 0

Sheet Juillet
B1: TABLEAU MENSUEL
B2: ='TABLEAU ANNUEL'!B2 -> 2026
B3: {=_xlfn.TEXTAFTER(CELL("nomfichier",B3),"x]")} -> Juillet
F4: =UPPER(F23)
B5: REVENUS REEL TOTAL | H5: DEPENSE RÉELLE TOTALE | L5: SOLDE PRECEDENT
B6: =G24 -> 853.81 | H6: =SUM(G25:G29) -> 1108 | L6: =Juin!B14 -> 3675.54
B9: LE SOLDE BUDGETISE | H9: PREVISION ECONOMIE MENSUELLE (budget) | L9: OBJECTIF ECONOMIE MENSUELLE
B10: =L6+H10 -> 3675.54 | H10: =E24-SUM(E25:F29) -> 0 | L10: 10
B13: LE SOLDE | H13: ECONOMIE MENSUELLE REALISE | L13: OBJECTIF SOLDE
B14: =B6+L6-H6 -> 3421.35 | H14: =G30 -> -254.19 | L14: =L10+L6 -> 3685.54
B22: RÉSUMÉ DE BUDGET | L22: Dépense
B23: SOURCE | E23: BUDGET | G23: RÉEL | H23: ECART | L23: SOURCE | M23: DATE | N23: LIBELLE | O23: RÉEL | P23: BUDGET | Q23: ECART
B24: REVENUS | E24: =F92 -> 0 | G24: =E92 -> 853.81 | H24: =G24-E24 -> 853.81 | L24: {=_xlfn._xlws.FILTER(_xlfn.CHOOSECOLS(Transaction[],2,1,3,7),(Transaction[Année]=$B$2)*(Transaction[MOIS]=$B$3)*(Transaction[Dépense/Revenue]=L22),"")} -> RESTAURANT | M24: 46213 | N24: Restaurant Le Bistro Parisien | O24: 40.4 | P24: =O24 -> 40.4 | Q24: =P24-O24 -> 0
B25: DEPENSE | E25: =P91 -> 0 | G25: =O92 -> 1108 | H25: =G25-E25 -> 1108 | L25: TRANSPORT | M25: 46222 | N25: Abonnement transports RATP | O25: 42.66 | P25: =O25 -> 42.66 | Q25: =P25-O25 -> 0
L26: REMBOURSEMENT PRET | M26: 46218 | N26: Remboursement prêt immobilier | O26: 113.81 | P26: =O26 -> 113.81 | Q26: =P26-O26 -> 0
L27: REMUNERATION | M27: 46227 | N27: Salaire - Société ABC | O27: 115.24 | P27: =O27 -> 115.24 | Q27: =P27-O27 -> 0
L28: PRELEVEMENT ASSURANCE | M28: 46226 | N28: Prélèvement mensuel assurance habitation | O28: 123.54 | P28: =O28 -> 123.54 | Q28: =P28-O28 -> 0
L29: COURSES | M29: 46213 | N29: Courses alimentaires Carrefour | O29: 136.06 | P29: =O29 -> 136.06 | Q29: =P29-O29 -> 0
B30: MONTANTS RESTANT | E30: =E24-SUM(E25:F29) -> 0 | G30: =G24-SUM(G25:G29) -> -254.19 | H30: =H24-SUM(H25:I29) -> -254.19 | L30: LOYER | M30: 46221 | N30: Paiement loyer mensuel | O30: 142.89 | P30: =O30 -> 142.89 | Q30: =P30-O30 -> 0
L31: BON CADEAUX | M31: 46231 | N31: Carte cadeau Fnac | O31: 195.54 | P31: =O31 -> 195.54 | Q31: =P31-O31 -> 0
L32: COMMISSION | M32: 46218 | N32: Commission de mouvement | O32: 197.86 | P32: =O32 -> 197.86 | Q32: =P32-O32 -> 0
P33: =O33 -> 0 | Q33: =P33-O33 -> 0
P34: =O34 -> 0 | Q34: =P34-O34 -> 0
P35: =O35 -> 0 | Q35: =P35-O35 -> 0
P36: =O36 -> 0 | Q36: =P36-O36 -> 0
B37: revenue | P37: =O37 -> 0 | Q37: =P37-O37 -> 0
B38: SOURCES | C38: DATE | D38: LIBELLE | E38: RÉEL | F38: BUDGET | H38: Écart | I38: DÉPOSÉ SUR | P38: =O38 -> 0 | Q38: =P38-O38 -> 0
B39: {=_xlfn._xlws.FILTER(_xlfn.CHOOSECOLS(Transaction[],2,1,3,7),(Transaction[Année]=$B$2)*(Transaction[MOIS]=$B$3)*(Transaction[Dépense/Revenue]=B37),"")} -> STATION ESSENCE | C39: 46224 | D39: Station Total - carburant | E39: 853.81 | F39: =0 -> 0 | H39: =E39-F39 -> 853.81 | P39: =O39 -> 0 | Q39: =P39-O39 -> 0
F40: 0 | H40: =E40-F40 -> 0 | P40: =O40 -> 0 | Q40: =P40-O40 -> 0
F41: 0 | H41: =E41-F41 -> 0 | P41: =O41 -> 0 | Q41: =P41-O41 -> 0
F42: =E42 -> 0 | H42: =E42-F42 -> 0 | P42: =O42 -> 0 | Q42: =P42-O42 -> 0
F43: =E43 -> 0 | H43: =E43-F43 -> 0 | P43: =O43 -> 0 | Q43: =P43-O43 -> 0
F44: =E44 -> 0 | H44: =E44-F44 -> 0 | P44: =O44 -> 0 | Q44: =P44-O44 -> 0
F45: =E45 -> 0 | H45: =E45-F45 -> 0 | P45: =O45 -> 0 | Q45: =P45-O45 -> 0
F46: =E46 -> 0 | H46: =E46-F46 -> 0 | P46: =O46 -> 0 | Q46: =P46-O46 -> 0
F47: =E47 -> 0 | H47: =E47-F47 -> 0 | P47: =O47 -> 0 | Q47: =P47-O47 -> 0
F48: =E48 -> 0 | H48: =E48-F48 -> 0 | P48: =O48 -> 0 | Q48: =P48-O48 -> 0
F49: =E49 -> 0 | H49: =E49-F49 -> 0 | P49: =O49 -> 0 | Q49: =P49-O49 -> 0
F50: =E50 -> 0 | H50: =E50-F50 -> 0 | P50: =O50 -> 0 | Q50: =P50-O50 -> 0
F51: =E51 -> 0 | H51: =E51-F51 -> 0 | P51: =O51 -> 0 | Q51: =P51-O51 -> 0
F52: =E52 -> 0 | H52: =E52-F52 -> 0 | P52: =O52 -> 0 | Q52: =P52-O52 -> 0
F53: =E53 -> 0 | H53: =E53-F53 -> 0 | P53: =O53 -> 0 | Q53: =P53-O53 -> 0
... F91: =E91 -> 0 | H91: =E91-F91 -> 0 | P91: =O91 -> 0 | Q91: =P91-O91 -> 0
B92: TOTAL | E92: =SUM(E39:E91) -> 853.81 | F92: =SUM(F39:G91) -> 0 | H92: =E92-F92 -> 853.81 | L92: TOTAL | O92: =SUM(O24:O91) -> 1108 | P92: =SUM(P24:P91) -> 1108 | Q92: =O92-P92 -> 0

Sheet Août
B1: TABLEAU MENSUEL
B2: ='TABLEAU ANNUEL'!B2 -> 2026
B3: {=_xlfn.TEXTAFTER(CELL("nomfichier",B3),"x]")} -> Août
F4: =UPPER(F23)
B5: REVENUS REEL TOTAL | H5: DEPENSE RÉELLE TOTALE | L5: SOLDE PRECEDENT
B6: =G24 -> 6589.41 | H6: =SUM(G25:G29) -> 478.54 | L6: =Juillet!B14 -> 3421.35
B9: LE SOLDE BUDGETISE | H9: PREVISION ECONOMIE MENSUELLE (budget) | L9: OBJECTIF ECONOMIE MENSUELLE
B10: =L6+H10 -> 4413.45 | H10: =E24-SUM(E25:F29) -> 992.1 | L10: 10
B13: LE SOLDE | H13: ECONOMIE MENSUELLE REALISE | L13: OBJECTIF SOLDE
B14: =B6+L6-H6 -> 9532.22 | H14: =G30 -> 6110.87 | L14: =L10+L6 -> 3431.35
B22: RÉSUMÉ DE BUDGET | L22: Dépense
B23: SOURCE | E23: BUDGET | G23: RÉEL | H23: ECART | L23: SOURCE | M23: DATE | N23: LIBELLE | O23: RÉEL | P23: BUDGET | Q23: ECART
B24: REVENUS | E24: =F92 -> 992.1 | G24: =E92 -> 6589.41 | H24: =G24-E24 -> 5597.31 | L24: {=_xlfn._xlws.FILTER(_xlfn.CHOOSECOLS(Transaction[],2,1,3,7),(Transaction[Année]=$B$2)*(Transaction[MOIS]=$B$3)*(Transaction[Dépense/Revenue]=L22),"")} -> CINEMA | M24: 46262 | N24: Place de cinéma UGC | O24: 20.55 | P24: =O24 -> 20.55 | Q24: =P24-O24 -> 0
B25: DEPENSE | E25: =P91 -> 0 | G25: =O92 -> 478.54 | H25: =G25-E25 -> 478.54 | L25: CINEMA | M25: 46240 | N25: Place de cinéma UGC | O25: 54.94 | P25: =O25 -> 54.94 | Q25: =P25-O25 -> 0
L26: LOYER | M26: 46239 | N26: Paiement loyer mensuel | O26: 116.26 | P26: =O26 -> 116.26 | Q26: =P26-O26 -> 0
L27: FRAIS BANCAIRES | M27: 46261 | N27: Frais de tenue de compte mensuels | O27: 119.72 | P27: =O27 -> 119.72 | Q27: =P27-O27 -> 0
L28: VIREMENT EMIS | M28: 46257 | N28: Virement émis vers compte épargne | O28: 167.07 | P28: =O28 -> 167.07 | Q28: =P28-O28 -> 0
P29: =O29 -> 0 | Q29: =P29-O29 -> 0
B30: MONTANTS RESTANT | E30: =E24-SUM(E25:F29) -> 992.1 | G30: =G24-SUM(G25:G29) -> 6110.87 | H30: =H24-SUM(H25:I29) -> 5118.77 | P30: =O30 -> 0 | Q30: =P30-O30 -> 0
P31: =O31 -> 0 | Q31: =P31-O31 -> 0
P32: =O32 -> 0 | Q32: =P32-O32 -> 0
P33: =O33 -> 0 | Q33: =P33-O33 -> 0
P34: =O34 -> 0 | Q34: =P34-O34 -> 0
P35: =O35 -> 0 | Q35: =P35-O35 -> 0
P36: =O36 -> 0 | Q36: =P36-O36 -> 0
B37: revenue | P37: =O37 -> 0 | Q37: =P37-O37 -> 0
B38: SOURCES | C38: DATE | D38: LIBELLE | E38: RÉEL | F38: BUDGET | H38: Écart | I38: DÉPOSÉ SUR | P38: =O38 -> 0 | Q38: =P38-O38 -> 0
B39: {=_xlfn._xlws.FILTER(_xlfn.CHOOSECOLS(Transaction[],2,1,3,7),(Transaction[Année]=$B$2)*(Transaction[MOIS]=$B$3)*(Transaction[Dépense/Revenue]=B37),"")} -> RESTAURANT | C39: 46242 | D39: Restaurant Le Bistro Parisien | E39: 2168.98 | F39: =0 -> 0 | H39: =E39-F39 -> 2168.98 | P39: =O39 -> 0 | Q39: =P39-O39 -> 0
B40: FACTURE TELEPHONE | C40: 46246 | D40: Paiement facture téléphonique SFR | E40: 1943.32 | F40: 0 | H40: =E40-F40 -> 1943.32 | P40: =O40 -> 0 | Q40: =P40-O40 -> 0
B41: PAIEMENT GOOGLE | C41: 46239 | D41: Paiement Google Play Store | E41: 1485.01 | F41: 0 | H41: =E41-F41 -> 1485.01 | P41: =O41 -> 0 | Q41: =P41-O41 -> 0
B42: ASSURANCE AUTO | C42: 46262 | D42: Prélèvement assurance automobile | E42: 992.1 | F42: =E42 -> 992.1 | H42: =E42-F42 -> 0 | P42: =O42 -> 0 | Q42: =P42-O42 -> 0
F43: =E43 -> 0 | H43: =E43-F43 -> 0 | P43: =O43 -> 0 | Q43: =P43-O43 -> 0
F44: =E44 -> 0 | H44: =E44-F44 -> 0 | P44: =O44 -> 0 | Q44: =P44-O44 -> 0
F45: =E45 -> 0 | H45: =E45-F45 -> 0 | P45: =O45 -> 0 | Q45: =P45-O45 -> 0
F46: =E46 -> 0 | H46: =E46-F46 -> 0 | P46: =O46 -> 0 | Q46: =P46-O46 -> 0
F47: =E47 -> 0 | H47: =E47-F47 -> 0 | P47: =O47 -> 0 | Q47: =P47-O47 -> 0
F48: =E48 -> 0 | H48: =E48-F48 -> 0 | P48: =O48 -> 0 | Q48: =P48-O48 -> 0
F49: =E49 -> 0 | H49: =E49-F49 -> 0 | P49: =O49 -> 0 | Q49: =P49-O49 -> 0
F50: =E50 -> 0 | H50: =E50-F50 -> 0 | P50: =O50 -> 0 | Q50: =P50-O50 -> 0
F51: =E51 -> 0 | H51: =E51-F51 -> 0 | P51: =O51 -> 0 | Q51: =P51-O51 -> 0
F52: =E52 -> 0 | H52: =E52-F52 -> 0 | P52: =O52 -> 0 | Q52: =P52-O52 -> 0
F53: =E53 -> 0 | H53: =E53-F53 -> 0 | P53: =O53 -> 0 | Q53: =P53-O53 -> 0
F54: =E54 -> 0 | H54: =E54-F54 -> 0 | P54: =O54 -> 0 | Q54: =P54-O54 -> 0
... F91: =E91 -> 0 | H91: =E91-F91 -> 0 | P91: =O91 -> 0 | Q91: =P91-O91 -> 0
B92: TOTAL | E92: =SUM(E39:E91) -> 6589.41 | F92: =SUM(F39:G91) -> 992.1 | H92: =E92-F92 -> 5597.31 | L92: TOTAL | O92: =SUM(O24:O91) -> 478.54 | P92: =SUM(P24:P91) -> 478.54 | Q92: =O92-P92 -> 0

Sheet Septembre
B1: TABLEAU MENSUEL
B2: ='TABLEAU ANNUEL'!B2 -> 2026
B3: {=_xlfn.TEXTAFTER(CELL("nomfichier",B3),"x]")} -> Septembre
F4: =UPPER(F23)
B5: REVENUS REEL TOTAL | H5: DEPENSE RÉELLE TOTALE | L5: SOLDE PRECEDENT
B6: =G24 -> 2567.54 | H6: =SUM(G25:G29) -> 507.07 | L6: =Août!B14 -> 9532.22
B9: LE SOLDE BUDGETISE | H9: PREVISION ECONOMIE MENSUELLE (budget) | L9: OBJECTIF ECONOMIE MENSUELLE
B10: =L6+H10 -> 9532.22 | H10: =E24-SUM(E25:F29) -> 0 | L10: 10
B13: LE SOLDE | H13: ECONOMIE MENSUELLE REALISE | L13: OBJECTIF SOLDE
B14: =B6+L6-H6 -> 11592.69 | H14: =G30 -> 2060.47 | L14: =L10+L6 -> 9542.22
B22: RÉSUMÉ DE BUDGET | L22: Dépense
B23: SOURCE | E23: BUDGET | G23: RÉEL | H23: ECART | L23: SOURCE | M23: DATE | N23: LIBELLE | O23: RÉEL | P23: BUDGET | Q23: ECART
B24: REVENUS | E24: =F92 -> 0 | G24: =E92 -> 2567.54 | H24: =G24-E24 -> 2567.54 | L24: {=_xlfn._xlws.FILTER(_xlfn.CHOOSECOLS(Transaction[],2,1,3,7),(Transaction[Année]=$B$2)*(Transaction[MOIS]=$B$3)*(Transaction[Dépense/Revenue]=L22),"")} -> TRANSPORT | M24: 46276 | N24: Abonnement transports RATP | O24: 90.98 | P24: =O24 -> 90.98 | Q24: =P24-O24 -> 0
B25: DEPENSE | E25: =P91 -> 0 | G25: =O92 -> 507.07 | H25: =G25-E25 -> 507.07 | L25: REMBOURSEMENT PRET | M25: 46272 | N25: Remboursement prêt immobilier | O25: 132.38 | P25: =O25 -> 132.38 | Q25: =P25-O25 -> 0
L26: FRAIS BANCAIRES | M26: 46289 | N26: Frais de tenue de compte mensuels | O26: 139.17 | P26: =O26 -> 139.17 | Q26: =P26-O26 -> 0
L27: PAIEMENT CARTE | M27: 46279 | N27: Paiement par carte bancaire | O27: 144.54 | P27: =O27 -> 144.54 | Q27: =P27-O27 -> 0
P28: =O28 -> 0 | Q28: =P28-O28 -> 0
P29: =O29 -> 0 | Q29: =P29-O29 -> 0
B30: MONTANTS RESTANT | E30: =E24-SUM(E25:F29) -> 0 | G30: =G24-SUM(G25:G29) -> 2060.47 | H30: =H24-SUM(H25:I29) -> 2060.47 | P30: =O30 -> 0 | Q30: =P30-O30 -> 0
P31: =O31 -> 0 | Q31: =P31-O31 -> 0
P32: =O32 -> 0 | Q32: =P32-O32 -> 0
P33: =O33 -> 0 | Q33: =P33-O33 -> 0
P34: =O34 -> 0 | Q34: =P34-O34 -> 0
P35: =O35 -> 0 | Q35: =P35-O35 -> 0
P36: =O36 -> 0 | Q36: =P36-O36 -> 0
B37: revenue | P37: =O37 -> 0 | Q37: =P37-O37 -> 0
B38: SOURCES | C38: DATE | D38: LIBELLE | E38: RÉEL | F38: BUDGET | H38: Écart | I38: DÉPOSÉ SUR | P38: =O38 -> 0 | Q38: =P38-O38 -> 0
B39: {=_xlfn._xlws.FILTER(_xlfn.CHOOSECOLS(Transaction[],2,1,3,7),(Transaction[Année]=$B$2)*(Transaction[MOIS]=$B$3)*(Transaction[Dépense/Revenue]=B37),"")} -> RETRAIT DAB | C39: 46278 | D39: Retrait au distributeur automatique | E39: 2567.54 | F39: =0 -> 0 | H39: =E39-F39 -> 2567.54 | P39: =O39 -> 0 | Q39: =P39-O39 -> 0
F40: 0 | H40: =E40-F40 -> 0 | P40: =O40 -> 0 | Q40: =P40-O40 -> 0
F41: 0 | H41: =E41-F41 -> 0 | P41: =O41 -> 0 | Q41: =P41-O41 -> 0
F42: =E42 -> 0 | H42: =E42-F42 -> 0 | P42: =O42 -> 0 | Q42: =P42-O42 -> 0
F43: =E43 -> 0 | H43: =E43-F43 -> 0 | P43: =O43 -> 0 | Q43: =P43-O43 -> 0
F44: =E44 -> 0 | H44: =E44-F44 -> 0 | P44: =O44 -> 0 | Q44: =P44-O44 -> 0
F45: =E45 -> 0 | H45: =E45-F45 -> 0 | P45: =O45 -> 0 | Q45: =P45-O45 -> 0
F46: =E46 -> 0 | H46: =E46-F46 -> 0 | P46: =O46 -> 0 | Q46: =P46-O46 -> 0
F47: =E47 -> 0 | H47: =E47-F47 -> 0 | P47: =O47 -> 0 | Q47: =P47-O47 -> 0
F48: =E48 -> 0 | H48: =E48-F48 -> 0 | P48: =O48 -> 0 | Q48: =P48-O48 -> 0
F49: =E49 -> 0 | H49: =E49-F49 -> 0 | P49: =O49 -> 0 | Q49: =P49-O49 -> 0
F50: =E50 -> 0 | H50: =E50-F50 -> 0 | P50: =O50 -> 0 | Q50: =P50-O50 -> 0
F51: =E51 -> 0 | H51: =E51-F51 -> 0 | P51: =O51 -> 0 | Q51: =P51-O51 -> 0
F52: =E52 -> 0 | H52: =E52-F52 -> 0 | P52: =O52 -> 0 | Q52: =P52-O52 -> 0
F53: =E53 -> 0 | H53: =E53-F53 -> 0 | P53: =O53 -> 0 | Q53: =P53-O53 -> 0
... F91: =E91 -> 0 | H91: =E91-F91 -> 0 | P91: =O91 -> 0 | Q91: =P91-O91 -> 0
B92: TOTAL | E92: =SUM(E39:E91) -> 2567.54 | F92: =SUM(F39:G91) -> 0 | H92: =E92-F92 -> 2567.54 | L92: TOTAL | O92: =SUM(O24:O91) -> 507.07 | P92: =SUM(P24:P91) -> 507.07 | Q92: =O92-P92 -> 0

Sheet Octobre
B1: TABLEAU MENSUEL
B2: ='TABLEAU ANNUEL'!B2 -> 2026
B3: {=_xlfn.TEXTAFTER(CELL("nomfichier",B3),"x]")} -> Octobre
F4: =UPPER(F23)
B5: REVENUS REEL TOTAL | H5: DEPENSE RÉELLE TOTALE | L5: SOLDE PRECEDENT
B6: =G24 -> 2200.61 | H6: =SUM(G25:G29) -> 806.26 | L6: =Septembre!B14 -> 11592.69
B9: LE SOLDE BUDGETISE | H9: PREVISION ECONOMIE MENSUELLE (budget) | L9: OBJECTIF ECONOMIE MENSUELLE
B10: =L6+H10 -> 11592.69 | H10: =E24-SUM(E25:F29) -> 0 | L10: 10
B13: LE SOLDE | H13: ECONOMIE MENSUELLE REALISE | L13: OBJECTIF SOLDE
B14: =B6+L6-H6 -> 12987.04 | H14: =G30 -> 1394.35 | L14: =L10+L6 -> 11602.69
B22: RÉSUMÉ DE BUDGET | L22: Dépense
B23: SOURCE | E23: BUDGET | G23: RÉEL | H23: ECART | L23: SOURCE | M23: DATE | N23: LIBELLE | O23: RÉEL | P23: BUDGET | Q23: ECART
B24: REVENUS | E24: =F92 -> 0 | G24: =E92 -> 2200.61 | H24: =G24-E24 -> 2200.61 | L24: {=_xlfn._xlws.FILTER(_xlfn.CHOOSECOLS(Transaction[],2,1,3,7),(Transaction[Année]=$B$2)*(Transaction[MOIS]=$B$3)*(Transaction[Dépense/Revenue]=L22),"")} -> CINEMA | M24: 46303 | N24: Place de cinéma UGC | O24: 22.41 | P24: =O24 -> 22.41 | Q24: =P24-O24 -> 0
B25: DEPENSE | E25: =P91 -> 0 | G25: =O92 -> 806.26 | H25: =G25-E25 -> 806.26 | L25: VIR SEPA RECU | M25: 46306 | N25: Virement reçu de Mr Dupont Jean | O25: 41.22 | P25: =O25 -> 41.22 | Q25: =P25-O25 -> 0
L26: ABONNEMENT NETFLIX | M26: 46325 | N26: Abonnement Netflix mensuel | O26: 50.94 | P26: =O26 -> 50.94 | Q26: =P26-O26 -> 0
L27: REMUNERATION | M27: 46320 | N27: Salaire - Société ABC | O27: 87.52 | P27: =O27 -> 87.52 | Q27: =P27-O27 -> 0
L28: COURSES | M28: 46303 | N28: Courses alimentaires Carrefour | O28: 123.37 | P28: =O28 -> 123.37 | Q28: =P28-O28 -> 0
L29: PAIEMENT CARTE | M29: 46300 | N29: Paiement par carte bancaire | O29: 124.98 | P29: =O29 -> 124.98 | Q29: =P29-O29 -> 0
B30: MONTANTS RESTANT | E30: =E24-SUM(E25:F29) -> 0 | G30: =G24-SUM(G25:G29) -> 1394.35 | H30: =H24-SUM(H25:I29) -> 1394.35 | L30: CB SUPERMARCHE | M30: 46303 | N30: Paiement carte supermarché Leclerc | O30: 172.78 | P30: =O30 -> 172.78 | Q30: =P30-O30 -> 0
L31: CINEMA | M31: 46312 | N31: Place de cinéma UGC | O31: 183.04 | P31: =O31 -> 183.04 | Q31: =P31-O31 -> 0
P32: =O32 -> 0 | Q32: =P32-O32 -> 0
P33: =O33 -> 0 | Q33: =P33-O33 -> 0
P34: =O34 -> 0 | Q34: =P34-O34 -> 0
P35: =O35 -> 0 | Q35: =P35-O35 -> 0
P36: =O36 -> 0 | Q36: =P36-O36 -> 0
B37: revenue | P37: =O37 -> 0 | Q37: =P37-O37 -> 0
B38: SOURCES | C38: DATE | D38: LIBELLE | E38: RÉEL | F38: BUDGET | H38: Écart | I38: DÉPOSÉ SUR | P38: =O38 -> 0 | Q38: =P38-O38 -> 0
B39: {=_xlfn._xlws.FILTER(_xlfn.CHOOSECOLS(Transaction[],2,1,3,7),(Transaction[Année]=$B$2)*(Transaction[MOIS]=$B$3)*(Transaction[Dépense/Revenue]=B37),"")} -> PAIEMENT EN LIGNE | C39: 46319 | D39: Paiement en ligne - sites divers | E39: 2200.61 | F39: =0 -> 0 | H39: =E39-F39 -> 2200.61 | P39: =O39 -> 0 | Q39: =P39-O39 -> 0
F40: 0 | H40: =E40-F40 -> 0 | P40: =O40 -> 0 | Q40: =P40-O40 -> 0
F41: 0 | H41: =E41-F41 -> 0 | P41: =O41 -> 0 | Q41: =P41-O41 -> 0
F42: =E42 -> 0 | H42: =E42-F42 -> 0 | P42: =O42 -> 0 | Q42: =P42-O42 -> 0
F43: =E43 -> 0 | H43: =E43-F43 -> 0 | P43: =O43 -> 0 | Q43: =P43-O43 -> 0
F44: =E44 -> 0 | H44: =E44-F44 -> 0 | P44: =O44 -> 0 | Q44: =P44-O44 -> 0
F45: =E45 -> 0 | H45: =E45-F45 -> 0 | P45: =O45 -> 0 | Q45: =P45-O45 -> 0
F46: =E46 -> 0 | H46: =E46-F46 -> 0 | P46: =O46 -> 0 | Q46: =P46-O46 -> 0
F47: =E47 -> 0 | H47: =E47-F47 -> 0 | P47: =O47 -> 0 | Q47: =P47-O47 -> 0
F48: =E48 -> 0 | H48: =E48-F48 -> 0 | P48: =O48 -> 0 | Q48: =P48-O48 -> 0
F49: =E49 -> 0 | H49: =E49-F49 -> 0 | P49: =O49 -> 0 | Q49: =P49-O49 -> 0
F50: =E50 -> 0 | H50: =E50-F50 -> 0 | P50: =O50 -> 0 | Q50: =P50-O50 -> 0
F51: =E51 -> 0 | H51: =E51-F51 -> 0 | P51: =O51 -> 0 | Q51: =P51-O51 -> 0
F52: =E52 -> 0 | H52: =E52-F52 -> 0 | P52: =O52 -> 0 | Q52: =P52-O52 -> 0
F53: =E53 -> 0 | H53: =E53-F53 -> 0 | P53: =O53 -> 0 | Q53: =P53-O53 -> 0
... F91: =E91 -> 0 | H91: =E91-F91 -> 0 | P91: =O91 -> 0 | Q91: =P91-O91 -> 0
B92: TOTAL | E92: =SUM(E39:E91) -> 2200.61 | F92: =SUM(F39:G91) -> 0 | H92: =E92-F92 -> 2200.61 | L92: TOTAL | O92: =SUM(O24:O91) -> 806.26 | P92: =SUM(P24:P91) -> 806.26 | Q92: =O92-P92 -> 0

Sheet Novembre
B1: TABLEAU MENSUEL
B2: ='TABLEAU ANNUEL'!B2 -> 2026
B3: {=_xlfn.TEXTAFTER(CELL("nomfichier",B3),"x]")} -> Novembre
F4: =UPPER(F23)
B5: REVENUS REEL TOTAL | H5: DEPENSE RÉELLE TOTALE | L5: SOLDE PRECEDENT
B6: =G24 -> 8244.61 | H6: =SUM(G25:G29) -> 582.25 | L6: =Octobre!B14 -> 12987.04
B9: LE SOLDE BUDGETISE | H9: PREVISION ECONOMIE MENSUELLE (budget) | L9: OBJECTIF ECONOMIE MENSUELLE
B10: =L6+H10 -> 14428.22 | H10: =E24-SUM(E25:F29) -> 1441.18 | L10: 10
B13: LE SOLDE | H13: ECONOMIE MENSUELLE REALISE | L13: OBJECTIF SOLDE
B14: =B6+L6-H6 -> 20649.4 | H14: =G30 -> 7662.36 | L14: =L10+L6 -> 12997.04
B22: RÉSUMÉ DE BUDGET | L22: Dépense
B23: SOURCE | E23: BUDGET | G23: RÉEL | H23: ECART | L23: SOURCE | M23: DATE | N23: LIBELLE | O23: RÉEL | P23: BUDGET | Q23: ECART
B24: REVENUS | E24: =F92 -> 1441.18 | G24: =E92 -> 8244.61 | H24: =G24-E24 -> 6803.43 | L24: {=_xlfn._xlws.FILTER(_xlfn.CHOOSECOLS(Transaction[],2,1,3,7),(Transaction[Année]=$B$2)*(Transaction[MOIS]=$B$3)*(Transaction[Dépense/Revenue]=L22),"")} -> ASSURANCE AUTO | M24: 46356 | N24: Prélèvement assurance automobile | O24: 79.15 | P24: =O24 -> 79.15 | Q24: =P24-O24 -> 0
B25: DEPENSE | E25: =P91 -> 0 | G25: =O92 -> 582.25 | H25: =G25-E25 -> 582.25 | L25: STATION ESSENCE | M25: 46353 | N25: Station Total - carburant | O25: 80.88 | P25: =O25 -> 80.88 | Q25: =P25-O25 -> 0
L26: COURSES | M26: 46348 | N26: Courses alimentaires Carrefour | O26: 104.73 | P26: =O26 -> 104.73 | Q26: =P26-O26 -> 0
L27: LOYER | M27: 46352 | N27: Paiement loyer mensuel | O27: 149.75 | P27: =O27 -> 149.75 | Q27: =P27-O27 -> 0
L28: COMMISSION | M28: 46333 | N28: Commission de mouvement | O28: 167.74 | P28: =O28 -> 167.74 | Q28: =P28-O28 -> 0
P29: =O29 -> 0 | Q29: =P29-O29 -> 0
B30: MONTANTS RESTANT | E30: =E24-SUM(E25:F29) -> 1441.18 | G30: =G24-SUM(G25:G29) -> 7662.36 | H30: =H24-SUM(H25:I29) -> 6221.18 | P30: =O30 -> 0 | Q30: =P30-O30 -> 0
P31: =O31 -> 0 | Q31: =P31-O31 -> 0
P32: =O32 -> 0 | Q32: =P32-O32 -> 0
P33: =O33 -> 0 | Q33: =P33-O33 -> 0
P34: =O34 -> 0 | Q34: =P34-O34 -> 0
P35: =O35 -> 0 | Q35: =P35-O35 -> 0
P36: =O36 -> 0 | Q36: =P36-O36 -> 0
B37: revenue | P37: =O37 -> 0 | Q37: =P37-O37 -> 0
B38: SOURCES | C38: DATE | D38: LIBELLE | E38: RÉEL | F38: BUDGET | H38: Écart | I38: DÉPOSÉ SUR | P38: =O38 -> 0 | Q38: =P38-O38 -> 0
B39: {=_xlfn._xlws.FILTER(_xlfn.CHOOSECOLS(Transaction[],2,1,3,7),(Transaction[Année]=$B$2)*(Transaction[MOIS]=$B$3)*(Transaction[Dépense/Revenue]=B37),"")} -> TRANSPORT | C39: 46332 | D39: Abonnement transports RATP | E39: 2836.06 | F39: =0 -> 0 | H39: =E39-F39 -> 2836.06 | P39: =O39 -> 0 | Q39: =P39-O39 -> 0
B40: VIREMENT EMIS | C40: 46331 | D40: Virement émis vers compte épargne | E40: 2337.38 | F40: 0 | H40: =E40-F40 -> 2337.38 | P40: =O40 -> 0 | Q40: =P40-O40 -> 0
B41: PAIEMENT GOOGLE | C41: 46330 | D41: Paiement Google Play Store | E41: 1629.99 | F41: 0 | H41: =E41-F41 -> 1629.99 | P41: =O41 -> 0 | Q41: =P41-O41 -> 0
B42: LOYER | C42: 46350 | D42: Paiement loyer mensuel | E42: 1441.18 | F42: =E42 -> 1441.18 | H42: =E42-F42 -> 0 | P42: =O42 -> 0 | Q42: =P42-O42 -> 0
F43: =E43 -> 0 | H43: =E43-F43 -> 0 | P43: =O43 -> 0 | Q43: =P43-O43 -> 0
F44: =E44 -> 0 | H44: =E44-F44 -> 0 | P44: =O44 -> 0 | Q44: =P44-O44 -> 0
F45: =E45 -> 0 | H45: =E45-F45 -> 0 | P45: =O45 -> 0 | Q45: =P45-O45 -> 0
F46: =E46 -> 0 | H46: =E46-F46 -> 0 | P46: =O46 -> 0 | Q46: =P46-O46 -> 0
F47: =E47 -> 0 | H47: =E47-F47 -> 0 | P47: =O47 -> 0 | Q47: =P47-O47 -> 0
F48: =E48 -> 0 | H48: =E48-F48 -> 0 | P48: =O48 -> 0 | Q48: =P48-O48 -> 0
F49: =E49 -> 0 | H49: =E49-F49 -> 0 | P49: =O49 -> 0 | Q49: =P49-O49 -> 0
F50: =E50 -> 0 | H50: =E50-F50 -> 0 | P50: =O50 -> 0 | Q50: =P50-O50 -> 0
F51: =E51 -> 0 | H51: =E51-F51 -> 0 | P51: =O51 -> 0 | Q51: =P51-O51 -> 0
F52: =E52 -> 0 | H52: =E52-F52 -> 0 | P52: =O52 -> 0 | Q52: =P52-O52 -> 0
F53: =E53 -> 0 | H53: =E53-F53 -> 0 | P53: =O53 -> 0 | Q53: =P53-O53 -> 0
F54: =E54 -> 0 | H54: =E54-F54 -> 0 | P54: =O54 -> 0 | Q54: =P54-O54 -> 0
... F91: =E91 -> 0 | H91: =E91-F91 -> 0 | P91: =O91 -> 0 | Q91: =P91-O91 -> 0
B92: TOTAL | E92: =SUM(E39:E91) -> 8244.61 | F92: =SUM(F39:G91) -> 1441.18 | H92: =E92-F92 -> 6803.43 | L92: TOTAL | O92: =SUM(O24:O91) -> 582.25 | P92: =SUM(P24:P91) -> 582.25 | Q92: =O92-P92 -> 0

Sheet Décembre
B1: TABLEAU MENSUEL
B2: ='TABLEAU ANNUEL'!B2 -> 2026
B3: {=_xlfn.TEXTAFTER(CELL("nomfichier",B3),"x]")} -> Décembre
F4: =UPPER(F23)
B5: REVENUS REEL TOTAL | H5: DEPENSE RÉELLE TOTALE | L5: SOLDE PRECEDENT
B6: =G24 -> 1351.22 | H6: =SUM(G25:G29) -> 846.3 | L6: =Novembre!B14 -> 20649.4
B9: LE SOLDE BUDGETISE | H9: PREVISION ECONOMIE MENSUELLE (budget) | L9: OBJECTIF ECONOMIE MENSUELLE
B10: =L6+H10 -> 20649.4 | H10: =E24-SUM(E25:F29) -> 0 | L10: 200
B13: LE SOLDE | H13: ECONOMIE MENSUELLE REALISE | L13: OBJECTIF SOLDE
B14: =B6+L6-H6 -> 21154.32 | H14: =G30 -> 504.92 | L14: =L10+L6 -> 20849.4
B22: RÉSUMÉ DE BUDGET | L22: Dépense
B23: SOURCE | E23: BUDGET | G23: RÉEL | H23: ECART | L23: SOURCE | M23: DATE | N23: LIBELLE | O23: RÉEL | P23: BUDGET | Q23: ECART
B24: REVENUS | E24: =F92 -> 0 | G24: =E92 -> 1351.22 | H24: =G24-E24 -> 1351.22 | L24: {=_xlfn._xlws.FILTER(_xlfn.CHOOSECOLS(Transaction[],2,1,3,7),(Transaction[Année]=$B$2)*(Transaction[MOIS]=$B$3)*(Transaction[Dépense/Revenue]=L22),"")} -> ABONNEMENT NETFLIX | M24: 46371 | N24: Abonnement Netflix mensuel | O24: 6.21 | P24: =O24 -> 6.21 | Q24: =P24-O24 -> 0
B25: DEPENSE | E25: =P91 -> 0 | G25: =O92 -> 846.3 | H25: =G25-E25 -> 846.3 | L25: CB SUPERMARCHE | M25: 46362 | N25: Paiement carte supermarché Leclerc | O25: 14.81 | P25: =O25 -> 14.81 | Q25: =P25-O25 -> 0
L26: TRANSPORT | M26: 46368 | N26: Abonnement transports RATP | O26: 67.66 | P26: =O26 -> 67.66 | Q26: =P26-O26 -> 0
L27: FACTURE TELEPHONE | M27: 46364 | N27: Paiement facture téléphonique SFR | O27: 96.01 | P27: =O27 -> 96.01 | Q27: =P27-O27 -> 0
L28: VIREMENT EMIS | M28: 46383 | N28: Virement émis vers compte épargne | O28: 103.35 | P28: =O28 -> 103.35 | Q28: =P28-O28 -> 0
L29: TRANSPORT | M29: 46377 | N29: Abonnement transports RATP | O29: 109.51 | P29: =O29 -> 109.51 | Q29: =P29-O29 -> 0
B30: MONTANTS RESTANT | E30: =E24-SUM(E25:F29) -> 0 | G30: =G24-SUM(G25:G29) -> 504.92 | H30: =H24-SUM(H25:I29) -> 504.92 | L30: REMUNERATION | M30: 46361 | N30: Salaire - Société ABC | O30: 143.92 | P30: =O30 -> 143.92 | Q30: =P30-O30 -> 0
L31: CB SUPERMARCHE | M31: 46379 | N31: Paiement carte supermarché Leclerc | O31: 150.38 | P31: =O31 -> 150.38 | Q31: =P31-O31 -> 0
L32: RESTAURANT | M32: 46386 | N32: Restaurant Le Bistro Parisien | O32: 154.45 | P32: =O32 -> 154.45 | Q32: =P32-O32 -> 0
P33: =O33 -> 0 | Q33: =P33-O33 -> 0
P34: =O34 -> 0 | Q34: =P34-O34 -> 0
P35: =O35 -> 0 | Q35: =P35-O35 -> 0
P36: =O36 -> 0 | Q36: =P36-O36 -> 0
B37: revenue | P37: =O37 -> 0 | Q37: =P37-O37 -> 0
B38: SOURCES | C38: DATE | D38: LIBELLE | E38: RÉEL | F38: BUDGET | H38: Écart | I38: DÉPOSÉ SUR | P38: =O38 -> 0 | Q38: =P38-O38 -> 0
B39: {=_xlfn._xlws.FILTER(_xlfn.CHOOSECOLS(Transaction[],2,1,3,7),(Transaction[Année]=$B$2)*(Transaction[MOIS]=$B$3)*(Transaction[Dépense/Revenue]=B37),"")} -> ACHAT AMAZON | C39: 46365 | D39: Achat sur Amazon.fr - électronique | E39: 914.19 | F39: =0 -> 0 | H39: =E39-F39 -> 914.19 | P39: =O39 -> 0 | Q39: =P39-O39 -> 0
B40: REMBOURSEMENT PRET | C40: 46378 | D40: Remboursement prêt immobilier | E40: 437.03 | F40: 0 | H40: =E40-F40 -> 437.03 | P40: =O40 -> 0 | Q40: =P40-O40 -> 0
F41: 0 | H41: =E41-F41 -> 0 | P41: =O41 -> 0 | Q41: =P41-O41 -> 0
F42: =E42 -> 0 | H42: =E42-F42 -> 0 | P42: =O42 -> 0 | Q42: =P42-O42 -> 0
F43: =E43 -> 0 | H43: =E43-F43 -> 0 | P43: =O43 -> 0 | Q43: =P43-O43 -> 0
F44: =E44 -> 0 | H44: =E44-F44 -> 0 | P44: =O44 -> 0 | Q44: =P44-O44 -> 0
F45: =E45 -> 0 | H45: =E45-F45 -> 0 | P45: =O45 -> 0 | Q45: =P45-O45 -> 0
F46: =E46 -> 0 | H46: =E46-F46 -> 0 | P46: =O46 -> 0 | Q46: =P46-O46 -> 0
F47: =E47 -> 0 | H47: =E47-F47 -> 0 | P47: =O47 -> 0 | Q47: =P47-O47 -> 0
F48: =E48 -> 0 | H48: =E48-F48 -> 0 | P48: =O48 -> 0 | Q48: =P48-O48 -> 0
F49: =E49 -> 0 | H49: =E49-F49 -> 0 | P49: =O49 -> 0 | Q49: =P49-O49 -> 0
F50: =E50 -> 0 | H50: =E50-F50 -> 0 | P50: =O50 -> 0 | Q50: =P50-O50 -> 0
F51: =E51 -> 0 | H51: =E51-F51 -> 0 | P51: =O51 -> 0 | Q51: =P51-O51 -> 0
F52: =E52 -> 0 | H52: =E52-F52 -> 0 | P52: =O52 -> 0 | Q52: =P52-O52 -> 0
F53: =E53 -> 0 | H53: =E53-F53 -> 0 | P53: =O53 -> 0 | Q53: =P53-O53 -> 0
... F91: =E91 -> 0 | H91: =E91-F91 -> 0 | P91: =O91 -> 0 | Q91: =P91-O91 -> 0
B92: TOTAL | E92: =SUM(E39:E91) -> 1351.22 | F92: =SUM(F39:G91) -> 0 | H92: =E92-F92 -> 1351.22 | L92: TOTAL | O92: =SUM(O24:O91) -> 846.3 | P92: =SUM(P24:P91) -> 846.3 | Q92: =O92-P92 -> 0

Sheet Transaction
A1: Date operation | B1: Libelle court | C1: Libelle operation | D1: Débit euro | E1: Crédit euro | F1: Dépense/Revenue | G1: Montant de transaction | H1: Montant de l'opération | I1: MOIS | J1: Année | K1: Type operation | M1: Param_Path
A2: 44939 | B2: Dépense carte | C2: Supermarché | D2: -43.21 | F2: dépense | G2: 43.21 | H2: -43.21 | I2: janvier | J2: 2023 | K2: Achat alimentation | M2: {=_xlfn.TEXTBEFORE(CELL("filename"),"\[")} -> C:\Users\eleve04\Documents\Github\ProjetGithub\PROJECTS_NDOUDI_Nimrod\Suivi Budgétaire Personnel [PERSONAL]
A3: 44941 | B3: Virement reçu | C3: Salaire | E3: 2200 | F3: revenue | G3: 2200 | H3: 2200 | I3: janvier | J3: 2023 | K3: Revenu
A4: 44946 | B4: Dépense carte | C4: Cinéma | D4: -17 | F4: dépense | G4: 17 | H4: -17 | I4: janvier | J4: 2023 | K4: Loisirs
A5: 44952 | B5: Prélèvement | C5: Facture Mobile | D5: -26.4 | F5: dépense | G5: 26.4 | H5: -26.4 | I5: janvier | J5: 2023 | K5: Télécom
A6: 44987 | B6: Prélèvement | C6: Assurance habitation | D6: -18.99 | F6: dépense | G6: 18.99 | H6: -18.99 | I6: mars | J6: 2023 | K6: Assurance
A7: 45140 | B7: Virement reçu | C7: Remboursement ami | E7: 95 | F7: revenue | G7: 95 | H7: 95 | I7: août | J7: 2023 | K7: Remboursement
A8: 44971 | B8: Dépense carte | C8: Transports urbains | D8: -38.5 | F8: dépense | G8: 38.5 | H8: -38.5 | I8: février | J8: 2023 | K8: Transport
A9: 44976 | B9: Dépense carte | C9: Boulangerie | D9: -6.5 | F9: dépense | G9: 6.5 | H9: -6.5 | I9: février | J9: 2023 | K9: Achat alimentation
A10: 44980 | B10: Prélèvement | C10: Facture Electricité | D10: -67.2 | F10: dépense | G10: 67.2 | H10: -67.2 | I10: février | J10: 2023 | K10: Electricité
A11: 44985 | B11: Dépense carte | C11: Pharmacie | D11: -18.9 | F11: dépense | G11: 18.9 | H11: -18.9 | I11: février | J11: 2023 | K11: Santé
A12: 45019 | B12: Virement reçu | C12: Prime | E12: 320 | F12: revenue | G12: 320 | H12: 320 | I12: avril | J12: 2023 | K12: Revenu
A13: 45141 | B13: Retrait DAB | C13: Distributeur | D13: -60 | F13: dépense | G13: 60 | H13: -60 | I13: août | J13: 2023 | K13: Retrait
A14: 44998 | B14: Dépense carte | C14: Achat internet | D14: -47.55 | F14: dépense | G14: 47.55 | H14: -47.55 | I14: mars | J14: 2023 | K14: Achat en ligne
A15: 45007 | B15: Virement reçu | C15: Remboursement impôt | E15: 360 | F15: revenue | G15: 360 | H15: 360 | I15: mars | J15: 2023 | K15: Remboursement
A16: 44930 | B16: Prélèvement | C16: Échéance prêt | D16: -467 | F16: dépense | G16: 467 | H16: -467 | I16: janvier | J16: 2023 | K16: Prêt
A17: 45234 | B17: Dépense carte | C17: Restaurant | D17: -59 | F17: dépense | G17: 59 | H17: -59 | I17: novembre | J17: 2023 | K17: Loisirs
A18: 45032 | B18: Dépense carte | C18: Supermarché | D18: -78 | F18: dépense | G18: 78 | H18: -78 | I18: avril | J18: 2023 | K18: Achat alimentation
A19: 45039 | B19: Virement reçu | C19: Cadeau | E19: 150 | F19: revenue | G19: 150 | H19: 150 | I19: avril | J19: 2023 | K19: Revenu
A20: 45046 | B20: Prélèvement | C20: Complémentaire santé | D20: -41.5 | F20: dépense | G20: 41.5 | H20: -41.5 | I20: avril | J20: 2023 | K20: Assurance
A21: 44990 | B21: Dépense carte | C21: Achat numérique | D21: -13 | F21: dépense | G21: 13 | H21: -13 | I21: mars | J21: 2023 | K21: Achat en ligne
A22: 45064 | B22: Virement reçu | C22: Salaire | E22: 2260 | F22: revenue | G22: 2260 | H22: 2260 | I22: mai | J22: 2023 | K22: Revenu
A23: 44963 | B23: Prélèvement | C23: Facture Electricité | D23: -59.9 | F23: dépense | G23: 59.9 | H23: -59.9 | I23: février | J23: 2023 | K23: Electricité
A24: 45175 | B24: Dépense carte | C24: Boucherie | D24: -31.1 | F24: dépense | G24: 31.1 | H24: -31.1 | I24: septembre | J24: 2023 | K24: Achat alimentation
A25: 45094 | B25: Prélèvement | C25: Échéance prêt | D25: -467 | F25: dépense | G25: 467 | H25: -467 | I25: juin | J25: 2023 | K25: Prêt
A26: 45098 | B26: Dépense carte | C26: Bar | D26: -24.4 | F26: dépense | G26: 24.4 | H26: -24.4 | I26: juin | J26: 2023 | K26: Loisirs
A27: 44933 | B27: Virement reçu | C27: Remboursement ami | E27: 45 | F27: revenue | G27: 45 | H27: 45 | I27: janvier | J27: 2023 | K27: Remboursement
A28: 45267 | B28: Prélèvement | C28: Facture Mobile | D28: -18.99 | F28: dépense | G28: 18.99 | H28: -18.99 | I28: décembre | J28: 2023 | K28: Télécom
A29: 45124 | B29: Dépense carte | C29: Fromagerie | D29: -25.4 | F29: dépense | G29: 25.4 | H29: -25.4 | I29: juillet | J29: 2023 | K29: Achat alimentation
A30: 45133 | B30: Virement reçu | C30: Prime | E30: 265 | F30: revenue | G30: 265 | H30: 265 | I30: juillet | J30: 2023 | K30: Revenu
A31: 45207 | B31: Prélèvement | C31: Assurance auto | D31: -16.8 | F31: dépense | G31: 16.8 | H31: -16.8 | I31: octobre | J31: 2023 | K31: Assurance
A32: 45161 | B32: Dépense carte | C32: Transports urbains | D32: -39.2 | F32: dépense | G32: 39.2 | H32: -39.2 | I32: août | J32: 2023 | K32: Transport
A33: 45165 | B33: Virement reçu | C33: Salaire | E33: 2245 | F33: revenue | G33: 2245 | H33: 2245 | I33: août | J33: 2023 | K33: Revenu
A34: 44994 | B34: Prélèvement | C34: Facture Electricité | D34: -62.3 | F34: dépense | G34: 62.3 | H34: -62.3 | I34: mars | J34: 2023 | K34: Electricité
A35: 45208 | B35: Dépense carte | C35: Pharmacie | D35: -11.6 | F35: dépense | G35: 11.6 | H35: -11.6 | I35: octobre | J35: 2023 | K35: Santé
A36: 45190 | B36: Prélèvement | C36: Échéance prêt | D36: -467 | F36: dépense | G36: 467 | H36: -467 | I36: septembre | J36: 2023 | K36: Prêt
A37: 45026 | B37: Virement reçu | C37: Remboursement assurance | E37: 180 | F37: revenue | G37: 180 | H37: 180 | I37: avril | J37: 2023 | K37: Remboursement
A38: 45218 | B38: Prélèvement | C38: Facture Mobile | D38: -19.99 | F38: dépense | G38: 19.99 | H38: -19.99 | I38: octobre | J38: 2023 | K38: Télécom
A39: 45224 | B39: Dépense carte | C39: Achat électronique | D39: -186.99 | F39: dépense | G39: 186.99 | H39: -186.99 | I39: octobre | J39: 2023 | K39: Achat en ligne
A40: 45230 | B40: Virement reçu | C40: Salaire | E40: 2280 | F40: revenue | G40: 2280 | H40: 2280 | I40: octobre | J40: 2023 | K40: Revenu
A41: 45149 | B41: Dépense carte | C41: Epicerie | D41: -42.8 | F41: dépense | G41: 42.8 | H41: -42.8 | I41: août | J41: 2023 | K41: Achat alimentation
A42: 45246 | B42: Dépense carte | C42: Théâtre | D42: -47 | F42: dépense | G42: 47 | H42: -47 | I42: novembre | J42: 2023 | K42: Loisirs
A43: 45251 | B43: Prélèvement | C43: Facture Electricité | D43: -69.45 | F43: dépense | G43: 69.45 | H43: -69.45 | I43: novembre | J43: 2023 | K43: Electricité
A44: 45089 | B44: Dépense carte | C44: Achat internet | D44: -54.9 | F44: dépense | G44: 54.9 | H44: -54.9 | I44: juin | J44: 2023 | K44: Achat en ligne
A45: 45279 | B45: Prélèvement | C45: Échéance prêt | D45: -467 | F45: dépense | G45: 467 | H45: -467 | I45: décembre | J45: 2023 | K45: Prêt
A46: 45289 | B46: Virement reçu | C46: Cadeau | E46: 500 | F46: revenue | G46: 500 | H46: 500 | I46: décembre | J46: 2023 | K46: Revenu
A47: 45444 | B47: Dépense carte | C47: Supermarché | D47: -62.2 | F47: dépense | G47: 62.2 | H47: -62.2 | I47: juin | J47: 2024 | K47: Achat alimentation
A48: 45306 | B48: Virement reçu | C48: Salaire | E48: 2290 | F48: revenue | G48: 2290 | H48: 2290 | I48: janvier | J48: 2024 | K48: Revenu
A49: 45314 | B49: Prélèvement | C49: Facture Mobile | D49: -19.99 | F49: dépense | G49: 19.99 | H49: -19.99 | I49: janvier | J49: 2024 | K49: Télécom
A50: 45598 | B50: Virement reçu | C50: Remboursement impôt | E50: 325 | F50: revenue | G50: 325 | H50: 325 | I50: novembre | J50: 2024 | K50: Remboursement
A51: 45342 | B51: Dépense carte | C51: Boulangerie | D51: -10.5 | F51: dépense | G51: 10.5 | H51: -10.5 | I51: février | J51: 2024 | K51: Achat alimentation
A52: 45325 | B52: Prélèvement | C52: Facture Electricité | D52: -67.2 | F52: dépense | G52: 67.2 | H52: -67.2 | I52: février | J52: 2024 | K52: Electricité
A53: 45568 | B53: Dépense carte | C53: Pharmacie | D53: -26.9 | F53: dépense | G53: 26.9 | H53: -26.9 | I53: octobre | J53: 2024 | K53: Santé
A54: 45372 | B54: Virement reçu | C54: Prime | E54: 380 | F54: revenue | G54: 380 | H54: 380 | I54: mars | J54: 2024 | K54: Revenu
A55: 45382 | B55: Prélèvement | C55: Échéance prêt | D55: -467 | F55: dépense | G55: 467 | H55: -467 | I55: mars | J55: 2024 | K55: Prêt
A56: 45539 | B56: Dépense carte | C56: Bar | D56: -18.35 | F56: dépense | G56: 18.35 | H56: -18.35 | I56: septembre | J56: 2024 | K56: Loisirs
A57: 45399 | B57: Dépense carte | C57: Achat numérique | D57: -34.1 | F57: dépense | G57: 34.1 | H57: -34.1 | I57: avril | J57: 2024 | K57: Achat en ligne
A58: 45409 | B58: Virement reçu | C58: Remboursement ami | E58: 65 | F58: revenue | G58: 65 | H58: 65 | I58: avril | J58: 2024 | K58: Remboursement
A59: 45448 | B59: Prélèvement | C59: Assurance habitation | D59: -19.55 | F59: dépense | G59: 19.55 | H59: -19.55 | I59: juin | J59: 2024 | K59: Assurance
A60: 45431 | B60: Dépense carte | C60: Supermarché | D60: -83.75 | F60: dépense | G60: 83.75 | H60: -83.75 | I60: mai | J60: 2024 | K60: Achat alimentation
A61: 45441 | B61: Dépense carte | C61: Cinéma | D61: -29 | F61: dépense | G61: 29 | H61: -29 | I61: mai | J61: 2024 | K61: Loisirs
A62: 45571 | B62: Virement reçu | C62: Salaire | E62: 2340 | F62: revenue | G62: 2340 | H62: 2340 | I62: octobre | J62: 2024 | K62: Revenu
A63: 45466 | B63: Prélèvement | C63: Facture Electricité | D63: -69.2 | F63: dépense | G63: 69.2 | H63: -69.2 | I63: juin | J63: 2024 | K63: Electricité
A64: 45419 | B64: Dépense carte | C64: Transports urbains | D64: -46.7 | F64: dépense | G64: 46.7 | H64: -46.7 | I64: mai | J64: 2024 | K64: Transport
A65: 45489 | B65: Prélèvement | C65: Échéance prêt | D65: -467 | F65: dépense | G65: 467 | H65: -467 | I65: juillet | J65: 2024 | K65: Prêt
A66: 45496 | B66: Virement reçu | C66: Prime | E66: 420 | F66: revenue | G66: 420 | H66: 420 | I66: juillet | J66: 2024 | K66: Revenu
A67: 45504 | B67: Prélèvement | C67: Facture Mobile | D67: -20.6 | F67: dépense | G67: 20.6 | H67: -20.6 | I67: juillet | J67: 2024 | K67: Télécom
A68: 45604 | B68: Dépense carte | C68: Achat internet | D68: -32.25 | F68: dépense | G68: 32.25 | H68: -32.25 | I68: novembre | J68: 2024 | K68: Achat en ligne
A69: 45525 | B69: Dépense carte | C69: Boucherie | D69: -39.3 | F69: dépense | G69: 39.3 | H69: -39.3 | I69: août | J69: 2024 | K69: Achat alimentation
A70: 45300 | B70: Prélèvement | C70: Assurance auto | D70: -15.4 | F70: dépense | G70: 15.4 | H70: -15.4 | I70: janvier | J70: 2024 | K70: Assurance
A71: 45550 | B71: Virement reçu | C71: Remboursement ami | E71: 110 | F71: revenue | G71: 110 | H71: 110 | I71: septembre | J71: 2024 | K71: Remboursement
A72: 45564 | B72: Dépense carte | C72: Théâtre | D72: -52 | F72: dépense | G72: 52 | H72: -52 | I72: septembre | J72: 2024 | K72: Loisirs
A73: 45636 | B73: Virement reçu | C73: Salaire | E73: 2375 | F73: revenue | G73: 2375 | H73: 2375 | I73: décembre | J73: 2024 | K73: Revenu
A74: 45589 | B74: Prélèvement | C74: Facture Electricité | D74: -70.8 | F74: dépense | G74: 70.8 | H74: -70.8 | I74: octobre | J74: 2024 | K74: Electricité
A75: 45484 | B75: Dépense carte | C75: Pharmacie | D75: -20.25 | F75: dépense | G75: 20.25 | H75: -20.25 | I75: juillet | J75: 2024 | K75: Santé
A76: 45616 | B76: Prélèvement | C76: Échéance prêt | D76: -467 | F76: dépense | G76: 467 | H76: -467 | I76: novembre | J76: 2024 | K76: Prêt
A77: 45394 | B77: Virement reçu | C77: Cadeau | E77: 250 | F77: revenue | G77: 250 | H77: 250 | I77: avril | J77: 2024 | K77: Revenu
A78: 45642 | B78: Prélèvement | C78: Facture Mobile | D78: -20.6 | F78: dépense | G78: 20.6 | H78: -20.6 | I78: décembre | J78: 2024 | K78: Télécom
A79: 45652 | B79: Dépense carte | C79: Cinéma | D79: -21.3 | F79: dépense | G79: 21.3 | H79: -21.3 | I79: décembre | J79: 2024 | K79: Loisirs
A80: 45717 | B80: Dépense carte | C80: Supermarché | D80: -70.8 | F80: dépense | G80: 70.8 | H80: -70.8 | I80: mars | J80: 2025 | K80: Achat alimentation
A81: 45672 | B81: Virement reçu | C81: Salaire | E81: 2400 | F81: revenue | G81: 2400 | H81: 2400 | I81: janvier | J81: 2025 | K81: Revenu
A82: 45679 | B82: Prélèvement | C82: Assurance habitation | D82: -22.1 | F82: dépense | G82: 22.1 | H82: -22.1 | I82: janvier | J82: 2025 | K82: Assurance
A83: 45690 | B83: Virement reçu | C83: Remboursement impôt | E83: 255 | F83: revenue | G83: 255 | H83: 255 | I83: février | J83: 2025 | K83: Remboursement
A84: 45963 | B84: Dépense carte | C84: Achat internet | D84: -23.5 | F84: dépense | G84: 23.5 | H84: -23.5 | I84: novembre | J84: 2025 | K84: Achat en ligne
A85: 45710 | B85: Prélèvement | C85: Échéance prêt | D85: -467 | F85: dépense | G85: 467 | H85: -467 | I85: février | J85: 2025 | K85: Prêt
A86: 45660 | B86: Dépense carte | C86: Théâtre | D86: -34 | F86: dépense | G86: 34 | H86: -34 | I86: janvier | J86: 2025 | K86: Loisirs
A87: 45730 | B87: Virement reçu | C87: Prime | E87: 400 | F87: revenue | G87: 400 | H87: 400 | I87: mars | J87: 2025 | K87: Revenu
A88: 45745 | B88: Dépense carte | C88: Boulangerie | D88: -19.1 | F88: dépense | G88: 19.1 | H88: -19.1 | I88: mars | J88: 2025 | K88: Achat alimentation
A89: 45751 | B89: Prélèvement | C89: Facture Electricité | D89: -72.5 | F89: dépense | G89: 72.5 | H89: -72.5 | I89: avril | J89: 2025 | K89: Electricité
A90: 45767 | B90: Dépense carte | C90: Restaurant | D90: -88 | F90: dépense | G90: 88 | H90: -88 | I90: avril | J90: 2025 | K90: Loisirs
A91: 45777 | B91: Virement reçu | C91: Salaire | E91: 2450 | F91: revenue | G91: 2450 | H91: 2450 | I91: avril | J91: 2025 | K91: Revenu
A92: 45996 | B92: Prélèvement | C92: Facture Mobile | D92: -22.1 | F92: dépense | G92: 22.1 | H92: -22.1 | I92: décembre | J92: 2025 | K92: Télécom
A93: 45801 | B93: Dépense carte | C93: Boucherie | D93: -33.4 | F93: dépense | G93: 33.4 | H93: -33.4 | I93: mai | J93: 2025 | K93: Achat alimentation
A94: 45906 | B94: Prélèvement | C94: Échéance prêt | D94: -467 | F94: dépense | G94: 467 | H94: -467 | I94: septembre | J94: 2025 | K94: Prêt
A95: 45829 | B95: Virement reçu | C95: Remboursement ami | E95: 220 | F95: revenue | G95: 220 | H95: 220 | I95: juin | J95: 2025 | K95: Remboursement
A96: 45784 | B96: Prélèvement | C96: Assurance auto | D96: -20.45 | F96: dépense | G96: 20.45 | H96: -20.45 | I96: mai | J96: 2025 | K96: Assurance
A97: 45856 | B97: Dépense carte | C97: Achat électronique | D97: -64.3 | F97: dépense | G97: 64.3 | H97: -64.3 | I97: juillet | J97: 2025 | K97: Achat en ligne
A98: 45868 | B98: Virement reçu | C98: Cadeau | E98: 560 | F98: revenue | G98: 560 | H98: 560 | I98: juillet | J98: 2025 | K98: Revenu
A99: 45883 | B99: Dépense carte | C99: Transports urbains | D99: -51.9 | F99: dépense | G99: 51.9 | H99: -51.9 | I99: août | J99: 2025 | K99: Transport
A100: 45899 | B100: Dépense carte | C100: Supermarché | D100: -67.1 | F100: dépense | G100: 67.1 | H100: -67.1 | I100: août | J100: 2025 | K100: Achat alimentation
...
